Workbook

Sheet Template
C1: Welcome to the Deep Value Hunter Stock Valuation Template!
D2: 1 Static, 2 Load, 3 Refresh | F2: 1 | G2: Static | H2: 2 | I2: Load | J2: 3 | K2: Refresh
C3: Load | E3: This sheet uses the DVH function from the Deep Value Hunter Add-On. Install the Extension from Extensions -> Add-Ons -> Get Add-Ons. Turn Iterative Calculation on in File -> Settings -> Calculation. Enter your ticker in C5 and switch C3 to "Load" to get data on your company! After data is loaded switch C3 to "Static" to lock the sheet. Use "Update" to refresh price data. Get more info at DeepValueHunter.com
C4: =C5
F5: =IFERROR(__xludf.DUMMYFUNCTION("IF($C$3=""Load"",iferror(GOOGLEFINANCE($C$5,""name"")),F5)"),"") | I5: Price Today | R5: Fair Value | S5: IRR | T5: Price ∆ | W5: ROIC (%)
I6: =IFERROR(__xludf.DUMMYFUNCTION("IF($C$3=""Static"", I6, iferror(GOOGLEFINANCE($C$5)))"),"") | Q6: Base Case | R6: =if(S6="No Forecast","",Q63) | S6: =if(countif(G63:H67,"=0")=10,"No Forecast", iferror(Q61,"No Forecast")) -> No Forecast | T6: =if(S6="No Forecast","",R6/I$6-1) | W6: =(F53)/(Q53) -> #VALUE!
Q7: Bear Case | R7: =if(S7="No Forecast","",Q71) | S7: =if(countif(G71:H75,"=0")=10,"No Forecast",iferror(Q69,"No Forecast")) -> No Forecast | T7: =if(S7="No Forecast","",R7/I$6-1)
C8: Last Update | D8: =IF($C$3="Static",D8,today()) -> 46213 | K8: 52 wk H | Q8: Bull Case | R8: =if(S8="No Forecast","",Q79) | S8: =if(countif(G79:H83,"=0")=10,"No Forecast",iferror(Q77,"No Forecast")) -> No Forecast | T8: =if(S8="No Forecast","",R8/I$6-1)
C9: Market cap | D9: =IFERROR(__xludf.DUMMYFUNCTION("IF($C$3=""Static"", D9, iferror(GOOGLEFINANCE($C$5,""marketcap"")))"),"") | K9: =IFERROR(__xludf.DUMMYFUNCTION("IF($C$3=""Load"",iferror(GOOGLEFINANCE($C$5,"""")),F5)"),"")
C10: P/E Ratio | E10: =IFERROR(D9/X53,"") | K10: 52 wk L | Q10: Margin of Safety | R10: 0.15 | S10: 0.2 | T10: 0.3
C11: EV / Operating Income | E11: =iferror(Q53/F53,"") | K11: =IFERROR(__xludf.DUMMYFUNCTION("IF($C$3=""Load"",iferror(GOOGLEFINANCE($C$5,"""")),F5)"),"") | Q11: Target Buy Price | R11: =$R6*(1-R10) -> 0 | S11: =$R6*(1-S10) -> 0 | T11: =$R6*(1-T10) -> 0
C12: Adj FCF Yield | E12: =iferror(K53/P53,"")
C13: Net Debt / Op Income | E13: =N53
C14: Operating Margin | E14: =G53 | L14: Base Case Implied IRR at Different Prices
C15: ROIC | E15: =IF($C$3="Load",if(DVH($C$5,C15)="Data not available",DVH($C$5,C15,2024),DVH($C$5,C15)),E15) -> No data available for | L15: =M15-(N15-M15) -> 0 | M15: =N15-(O15-N15) -> 0 | N15: =O15-(P15-O15) -> 0 | O15: =P15-(Q15-P15) -> 0 | P15: =round(I6,0) -> 0 | Q15: =P15+round($I6/10,0) -> 0 | R15: =Q15+Q15-P15 -> 0 | S15: =R15+R15-Q15 -> 0 | T15: =S15+S15-R15 -> 0
C16: Reporting Currency | E16: USD | L16: =iferror(IRR({-1*$P$53*(L15/$I$6),$I63,$I64,$I65,$I66,$I67+$N65}),"-") -> - | M16: =iferror(IRR({-1*$P$53*(M15/$I$6),$I63,$I64,$I65,$I66,$I67+$N65}),"-") -> - | N16: =iferror(IRR({-1*$P$53*(N15/$I$6),$I63,$I64,$I65,$I66,$I67+$N65}),"-") -> - | O16: =iferror(IRR({-1*$P$53*(O15/$I$6),$I63,$I64,$I65,$I66,$I67+$N65}),"-") -> - | P16: =iferror(IRR({-1*$P$53*(P15/$I$6),$I63,$I64,$I65,$I66,$I67+$N65}),"-") -> - | Q16: =iferror(IRR({-1*$P$53*(Q15/$I$6),$I63,$I64,$I65,$I66,$I67+$N65}),"-") -> - | R16: =iferror(IRR({-1*$P$53*(R15/$I$6),$I63,$I64,$I65,$I66,$I67+$N65}),"-") -> - | S16: =iferror(IRR({-1*$P$53*(S15/$I$6),$I63,$I64,$I65,$I66,$I67+$N65}),"-") -> - | T16: =iferror(IRR({-1*$P$53*(T15/$I$6),$I63,$I64,$I65,$I66,$I67+$N65}),"-") -> -
F20: Bear Case | G20: Base Case | H20: Bull Case
F21: =R7 | G21: =R6 | H21: =R8
F22: =I6 | G22: =I6 | H22: =I6
B32: Reporting Currency | C32: =IF(E16<>"USD", "Historical Data (converted to USD from " & E16 & ")", "Historical Data") -> Historical Data
B33: =E16 -> USD | D33: Revenue ($M) | E33: Y/Y ∆ | F33: Operating Income | G33: Operating Margin | H33: Operating Cash Flow | I33: Capex | J33: SBC | K33: Adj. FCF | L33: Adj. FCF Margin | M33: Net Debt | N33: Net Debt / EBIT | O33: Shares | P33: Market Cap | Q33: EV | R33: Adj. FCF Yield | S33: EV/EBIT | T33: Tangible Book | V33: Gross Profit | W33: Gross Margin | X33: Net Income | Y33: Net Margin | Z33: Op Inc - Net Inc | AA33: Gr Profit - Op Inc | AB33: Rev - Gr Profit
A34: 2007 | B34: {=INDEX('Currency Conversion'!$C$4:$L$23, MATCH(C34, 'Currency Conversion'!$B$4:$B$23, 0), MATCH($E$16, 'Currency Conversion'!$C$3:$L$3, 0))} -> 1 | C34: 2007 | D34: =IF($C$3="Load",DVH($C$5,"revenue",$C34)*$B34,D34) -> #VALUE! | F34: =IF($C$3="Load",DVH($C$5,"operatingincome",$C34)*$B34,F34) -> #VALUE! | G34: =iferror(F34/D34,"") | H34: =IF($C$3="Load",DVH($C$5,"operatingcashflow",$C34)*$B34,H34) -> #VALUE! | I34: =IF($C$3="Load",iferror(DVH($C$5,"capex",$C34)*$B34,""),I34) | J34: =IF($C$3="Load",iferror(DVH($C$5,"sharebasedcompensation",$C34)*$B34,""),J34) | K34: =iferror(H34-I34-J34,"") | L34: =iferror(K34/D34,"") | M34: =IF($C$3="Load",iferror($B34*DVH($C$5,"totaldebt",$C34),"")-iferror($B34*DVH($C$5,"cash",$C34),""),M34) -> 0 | N34: =iferror(M34/F34,"") | O34: =IF($C$3="Load",DVH($C$5,"Shares",$C34),O34) -> No data available for | P34: =IF($C$3="Load",DVH($C$5,"MarketCap",$C34),P34) -> No data available for | Q34: =IF($C$3="Load",DVH($C$5,"EnterpriseValue",$C34),Q34) -> No data available for | R34: =iferror(K34/P34,"") | S34: =iferror(Q34/F34,"") | T34: =IF($C$3="Load",$B34*DVH($C$5,"TangibleBookValue",$C34),T34) -> #VALUE! | V34: =iferror(IF($C$3="Load",DVH($C$5,"grossprofit",$C34)*$B34,V34),"") | W34: =iferror(V34/$D34,"") | X34: =iferror(IF($C$3="Load",DVH($C$5,"netincome",$C34)*$B34,X34),"") | Y34: =iferror(X34/$D34,"") | Z34: =iferror(if(X34<0,if(F34<0,0,F34),if(F34>X34,(F34-X34),0)),"") | AA34: =iferror(if(and(X34<0,F34<0),V34,V34-max(F34,X34)),"") | AB34: =iferror(D34-V34,"")
A35: 2008 | B35: {=INDEX('Currency Conversion'!$C$4:$L$23, MATCH(C35, 'Currency Conversion'!$B$4:$B$23, 0), MATCH($E$16, 'Currency Conversion'!$C$3:$L$3, 0))} -> 1 | C35: 2008 | D35: =IF($C$3="Load",DVH($C$5,"revenue",$C35)*$B35,D35) -> #VALUE! | E35: =iferror(D35/D34-1,"") | F35: =IF($C$3="Load",DVH($C$5,"operatingincome",$C35)*$B35,F35) -> #VALUE! | G35: =iferror(F35/D35,"") | H35: =IF($C$3="Load",DVH($C$5,"operatingcashflow",$C35)*$B35,H35) -> #VALUE! | I35: =IF($C$3="Load",iferror(DVH($C$5,"capex",$C35)*$B35,""),I35) | J35: =IF($C$3="Load",iferror(DVH($C$5,"sharebasedcompensation",$C35)*$B35,""),J35) | K35: =iferror(H35-I35-J35,"") | L35: =iferror(K35/D35,"") | M35: =IF($C$3="Load",iferror($B35*DVH($C$5,"totaldebt",$C35),"")-iferror($B35*DVH($C$5,"cash",$C35),""),M35) -> 0 | N35: =iferror(M35/F35,"") | O35: =IF($C$3="Load",DVH($C$5,"Shares",$C35),O35) -> No data available for | P35: =IF($C$3="Load",DVH($C$5,"MarketCap",$C35),P35) -> No data available for | Q35: =IF($C$3="Load",DVH($C$5,"EnterpriseValue",$C35),Q35) -> No data available for | R35: =iferror(K35/P35,"") | S35: =iferror(Q35/F35,"") | T35: =IF($C$3="Load",$B35*DVH($C$5,"TangibleBookValue",$C35),T35) -> #VALUE! | V35: =iferror(IF($C$3="Load",DVH($C$5,"grossprofit",$C35)*$B35,V35),"") | W35: =iferror(V35/$D35,"") | X35: =iferror(IF($C$3="Load",DVH($C$5,"netincome",$C35)*$B35,X35),"") | Y35: =iferror(X35/$D35,"") | Z35: =iferror(if(X35<0,if(F35<0,0,F35),if(F35>X35,(F35-X35),0)),"") | AA35: =iferror(if(and(X35<0,F35<0),V35,V35-max(F35,X35)),"") | AB35: =iferror(D35-V35,"")
A36: 2009 | B36: {=INDEX('Currency Conversion'!$C$4:$L$23, MATCH(C36, 'Currency Conversion'!$B$4:$B$23, 0), MATCH($E$16, 'Currency Conversion'!$C$3:$L$3, 0))} -> 1 | C36: 2009 | D36: =IF($C$3="Load",DVH($C$5,"revenue",$C36)*$B36,D36) -> #VALUE! | E36: =iferror(D36/D35-1,"") | F36: =IF($C$3="Load",DVH($C$5,"operatingincome",$C36)*$B36,F36) -> #VALUE! | G36: =iferror(F36/D36,"") | H36: =IF($C$3="Load",DVH($C$5,"operatingcashflow",$C36)*$B36,H36) -> #VALUE! | I36: =IF($C$3="Load",iferror(DVH($C$5,"capex",$C36)*$B36,""),I36) | J36: =IF($C$3="Load",iferror(DVH($C$5,"sharebasedcompensation",$C36)*$B36,""),J36) | K36: =iferror(H36-I36-J36,"") | L36: =iferror(K36/D36,"") | M36: =IF($C$3="Load",iferror($B36*DVH($C$5,"totaldebt",$C36),"")-iferror($B36*DVH($C$5,"cash",$C36),""),M36) -> 0 | N36: =iferror(M36/F36,"") | O36: =IF($C$3="Load",DVH($C$5,"Shares",$C36),O36) -> No data available for | P36: =IF($C$3="Load",DVH($C$5,"MarketCap",$C36),P36) -> No data available for | Q36: =IF($C$3="Load",DVH($C$5,"EnterpriseValue",$C36),Q36) -> No data available for | R36: =iferror(K36/P36,"") | S36: =iferror(Q36/F36,"") | T36: =IF($C$3="Load",$B36*DVH($C$5,"TangibleBookValue",$C36),T36) -> #VALUE! | V36: =iferror(IF($C$3="Load",DVH($C$5,"grossprofit",$C36)*$B36,V36),"") | W36: =iferror(V36/$D36,"") | X36: =iferror(IF($C$3="Load",DVH($C$5,"netincome",$C36)*$B36,X36),"") | Y36: =iferror(X36/$D36,"") | Z36: =iferror(if(X36<0,if(F36<0,0,F36),if(F36>X36,(F36-X36),0)),"") | AA36: =iferror(if(and(X36<0,F36<0),V36,V36-max(F36,X36)),"") | AB36: =iferror(D36-V36,"")
A37: 2010 | B37: {=INDEX('Currency Conversion'!$C$4:$L$23, MATCH(C37, 'Currency Conversion'!$B$4:$B$23, 0), MATCH($E$16, 'Currency Conversion'!$C$3:$L$3, 0))} -> 1 | C37: 2010 | D37: =IF($C$3="Load",DVH($C$5,"revenue",$C37)*$B37,D37) -> #VALUE! | E37: =iferror(D37/D36-1,"") | F37: =IF($C$3="Load",DVH($C$5,"operatingincome",$C37)*$B37,F37) -> #VALUE! | G37: =iferror(F37/D37,"") | H37: =IF($C$3="Load",DVH($C$5,"operatingcashflow",$C37)*$B37,H37) -> #VALUE! | I37: =IF($C$3="Load",iferror(DVH($C$5,"capex",$C37)*$B37,""),I37) | J37: =IF($C$3="Load",iferror(DVH($C$5,"sharebasedcompensation",$C37)*$B37,""),J37) | K37: =iferror(H37-I37-J37,"") | L37: =iferror(K37/D37,"") | M37: =IF($C$3="Load",iferror($B37*DVH($C$5,"totaldebt",$C37),"")-iferror($B37*DVH($C$5,"cash",$C37),""),M37) -> 0 | N37: =iferror(M37/F37,"") | O37: =IF($C$3="Load",DVH($C$5,"Shares",$C37),O37) -> No data available for | P37: =IF($C$3="Load",DVH($C$5,"MarketCap",$C37),P37) -> No data available for | Q37: =IF($C$3="Load",DVH($C$5,"EnterpriseValue",$C37),Q37) -> No data available for | R37: =iferror(K37/P37,"") | S37: =iferror(Q37/F37,"") | T37: =IF($C$3="Load",$B37*DVH($C$5,"TangibleBookValue",$C37),T37) -> #VALUE! | V37: =iferror(IF($C$3="Load",DVH($C$5,"grossprofit",$C37)*$B37,V37),"") | W37: =iferror(V37/$D37,"") | X37: =iferror(IF($C$3="Load",DVH($C$5,"netincome",$C37)*$B37,X37),"") | Y37: =iferror(X37/$D37,"") | Z37: =iferror(if(X37<0,if(F37<0,0,F37),if(F37>X37,(F37-X37),0)),"") | AA37: =iferror(if(and(X37<0,F37<0),V37,V37-max(F37,X37)),"") | AB37: =iferror(D37-V37,"")
A38: 2011 | B38: {=INDEX('Currency Conversion'!$C$4:$L$23, MATCH(C38, 'Currency Conversion'!$B$4:$B$23, 0), MATCH($E$16, 'Currency Conversion'!$C$3:$L$3, 0))} -> 1 | C38: 2011 | D38: =IF($C$3="Load",DVH($C$5,"revenue",$C38)*$B38,D38) -> #VALUE! | E38: =iferror(D38/D37-1,"") | F38: =IF($C$3="Load",DVH($C$5,"operatingincome",$C38)*$B38,F38) -> #VALUE! | G38: =iferror(F38/D38,"") | H38: =IF($C$3="Load",DVH($C$5,"operatingcashflow",$C38)*$B38,H38) -> #VALUE! | I38: =IF($C$3="Load",iferror(DVH($C$5,"capex",$C38)*$B38,""),I38) | J38: =IF($C$3="Load",iferror(DVH($C$5,"sharebasedcompensation",$C38)*$B38,""),J38) | K38: =iferror(H38-I38-J38,"") | L38: =iferror(K38/D38,"") | M38: =IF($C$3="Load",iferror($B38*DVH($C$5,"totaldebt",$C38),"")-iferror($B38*DVH($C$5,"cash",$C38),""),M38) -> 0 | N38: =iferror(M38/F38,"") | O38: =IF($C$3="Load",DVH($C$5,"Shares",$C38),O38) -> No data available for | P38: =IF($C$3="Load",DVH($C$5,"MarketCap",$C38),P38) -> No data available for | Q38: =IF($C$3="Load",DVH($C$5,"EnterpriseValue",$C38),Q38) -> No data available for | R38: =iferror(K38/P38,"") | S38: =iferror(Q38/F38,"") | T38: =IF($C$3="Load",$B38*DVH($C$5,"TangibleBookValue",$C38),T38) -> #VALUE! | V38: =iferror(IF($C$3="Load",DVH($C$5,"grossprofit",$C38)*$B38,V38),"") | W38: =iferror(V38/$D38,"") | X38: =iferror(IF($C$3="Load",DVH($C$5,"netincome",$C38)*$B38,X38),"") | Y38: =iferror(X38/$D38,"") | Z38: =iferror(if(X38<0,if(F38<0,0,F38),if(F38>X38,(F38-X38),0)),"") | AA38: =iferror(if(and(X38<0,F38<0),V38,V38-max(F38,X38)),"") | AB38: =iferror(D38-V38,"")
A39: 2012 | B39: {=INDEX('Currency Conversion'!$C$4:$L$23, MATCH(C39, 'Currency Conversion'!$B$4:$B$23, 0), MATCH($E$16, 'Currency Conversion'!$C$3:$L$3, 0))} -> 1 | C39: 2012 | D39: =IF($C$3="Load",DVH($C$5,"revenue",$C39)*$B39,D39) -> #VALUE! | E39: =iferror(D39/D38-1,"") | F39: =IF($C$3="Load",DVH($C$5,"operatingincome",$C39)*$B39,F39) -> #VALUE! | G39: =iferror(F39/D39,"") | H39: =IF($C$3="Load",DVH($C$5,"operatingcashflow",$C39)*$B39,H39) -> #VALUE! | I39: =IF($C$3="Load",iferror(DVH($C$5,"capex",$C39)*$B39,""),I39) | J39: =IF($C$3="Load",iferror(DVH($C$5,"sharebasedcompensation",$C39)*$B39,""),J39) | K39: =iferror(H39-I39-J39,"") | L39: =iferror(K39/D39,"") | M39: =IF($C$3="Load",iferror($B39*DVH($C$5,"totaldebt",$C39),"")-iferror($B39*DVH($C$5,"cash",$C39),""),M39) -> 0 | N39: =iferror(M39/F39,"") | O39: =IF($C$3="Load",DVH($C$5,"Shares",$C39),O39) -> No data available for | P39: =IF($C$3="Load",DVH($C$5,"MarketCap",$C39),P39) -> No data available for | Q39: =IF($C$3="Load",DVH($C$5,"EnterpriseValue",$C39),Q39) -> No data available for | R39: =iferror(K39/P39,"") | S39: =iferror(Q39/F39,"") | T39: =IF($C$3="Load",$B39*DVH($C$5,"TangibleBookValue",$C39),T39) -> #VALUE! | V39: =iferror(IF($C$3="Load",DVH($C$5,"grossprofit",$C39)*$B39,V39),"") | W39: =iferror(V39/$D39,"") | X39: =iferror(IF($C$3="Load",DVH($C$5,"netincome",$C39)*$B39,X39),"") | Y39: =iferror(X39/$D39,"") | Z39: =iferror(if(X39<0,if(F39<0,0,F39),if(F39>X39,(F39-X39),0)),"") | AA39: =iferror(if(and(X39<0,F39<0),V39,V39-max(F39,X39)),"") | AB39: =iferror(D39-V39,"")
A40: 2013 | B40: {=INDEX('Currency Conversion'!$C$4:$L$23, MATCH(C40, 'Currency Conversion'!$B$4:$B$23, 0), MATCH($E$16, 'Currency Conversion'!$C$3:$L$3, 0))} -> 1 | C40: 2013 | D40: =IF($C$3="Load",DVH($C$5,"revenue",$C40)*$B40,D40) -> #VALUE! | E40: =iferror(D40/D39-1,"") | F40: =IF($C$3="Load",DVH($C$5,"operatingincome",$C40)*$B40,F40) -> #VALUE! | G40: =iferror(F40/D40,"") | H40: =IF($C$3="Load",DVH($C$5,"operatingcashflow",$C40)*$B40,H40) -> #VALUE! | I40: =IF($C$3="Load",iferror(DVH($C$5,"capex",$C40)*$B40,""),I40) | J40: =IF($C$3="Load",iferror(DVH($C$5,"sharebasedcompensation",$C40)*$B40,""),J40) | K40: =iferror(H40-I40-J40,"") | L40: =iferror(K40/D40,"") | M40: =IF($C$3="Load",iferror($B40*DVH($C$5,"totaldebt",$C40),"")-iferror($B40*DVH($C$5,"cash",$C40),""),M40) -> 0 | N40: =iferror(M40/F40,"") | O40: =IF($C$3="Load",DVH($C$5,"Shares",$C40),O40) -> No data available for | P40: =IF($C$3="Load",DVH($C$5,"MarketCap",$C40),P40) -> No data available for | Q40: =IF($C$3="Load",DVH($C$5,"EnterpriseValue",$C40),Q40) -> No data available for | R40: =iferror(K40/P40,"") | S40: =iferror(Q40/F40,"") | T40: =IF($C$3="Load",$B40*DVH($C$5,"TangibleBookValue",$C40),T40) -> #VALUE! | V40: =iferror(IF($C$3="Load",DVH($C$5,"grossprofit",$C40)*$B40,V40),"") | W40: =iferror(V40/$D40,"") | X40: =iferror(IF($C$3="Load",DVH($C$5,"netincome",$C40)*$B40,X40),"") | Y40: =iferror(X40/$D40,"") | Z40: =iferror(if(X40<0,if(F40<0,0,F40),if(F40>X40,(F40-X40),0)),"") | AA40: =iferror(if(and(X40<0,F40<0),V40,V40-max(F40,X40)),"") | AB40: =iferror(D40-V40,"")
A41: 2014 | B41: {=INDEX('Currency Conversion'!$C$4:$L$23, MATCH(C41, 'Currency Conversion'!$B$4:$B$23, 0), MATCH($E$16, 'Currency Conversion'!$C$3:$L$3, 0))} -> 1 | C41: 2014 | D41: =IF($C$3="Load",DVH($C$5,"revenue",$C41)*$B41,D41) -> #VALUE! | E41: =iferror(D41/D40-1,"") | F41: =IF($C$3="Load",DVH($C$5,"operatingincome",$C41)*$B41,F41) -> #VALUE! | G41: =iferror(F41/D41,"") | H41: =IF($C$3="Load",DVH($C$5,"operatingcashflow",$C41)*$B41,H41) -> #VALUE! | I41: =IF($C$3="Load",iferror(DVH($C$5,"capex",$C41)*$B41,""),I41) | J41: =IF($C$3="Load",iferror(DVH($C$5,"sharebasedcompensation",$C41)*$B41,""),J41) | K41: =iferror(H41-I41-J41,"") | L41: =iferror(K41/D41,"") | M41: =IF($C$3="Load",iferror($B41*DVH($C$5,"totaldebt",$C41),"")-iferror($B41*DVH($C$5,"cash",$C41),""),M41) -> 0 | N41: =iferror(M41/F41,"") | O41: =IF($C$3="Load",DVH($C$5,"Shares",$C41),O41) -> No data available for | P41: =IF($C$3="Load",DVH($C$5,"MarketCap",$C41),P41) -> No data available for | Q41: =IF($C$3="Load",DVH($C$5,"EnterpriseValue",$C41),Q41) -> No data available for | R41: =iferror(K41/P41,"") | S41: =iferror(Q41/F41,"") | T41: =IF($C$3="Load",$B41*DVH($C$5,"TangibleBookValue",$C41),T41) -> #VALUE! | V41: =iferror(IF($C$3="Load",DVH($C$5,"grossprofit",$C41)*$B41,V41),"") | W41: =iferror(V41/$D41,"") | X41: =iferror(IF($C$3="Load",DVH($C$5,"netincome",$C41)*$B41,X41),"") | Y41: =iferror(X41/$D41,"") | Z41: =iferror(if(X41<0,if(F41<0,0,F41),if(F41>X41,(F41-X41),0)),"") | AA41: =iferror(if(and(X41<0,F41<0),V41,V41-max(F41,X41)),"") | AB41: =iferror(D41-V41,"")
A42: 2015 | B42: {=INDEX('Currency Conversion'!$C$4:$L$23, MATCH(C42, 'Currency Conversion'!$B$4:$B$23, 0), MATCH($E$16, 'Currency Conversion'!$C$3:$L$3, 0))} -> 1 | C42: 2015 | D42: =IF($C$3="Load",DVH($C$5,"revenue",$C42)*$B42,D42) -> #VALUE! | E42: =iferror(D42/D41-1,"") | F42: =IF($C$3="Load",DVH($C$5,"operatingincome",$C42)*$B42,F42) -> #VALUE! | G42: =iferror(F42/D42,"") | H42: =IF($C$3="Load",DVH($C$5,"operatingcashflow",$C42)*$B42,H42) -> #VALUE! | I42: =IF($C$3="Load",iferror(DVH($C$5,"capex",$C42)*$B42,""),I42) | J42: =IF($C$3="Load",iferror(DVH($C$5,"sharebasedcompensation",$C42)*$B42,""),J42) | K42: =iferror(H42-I42-J42,"") | L42: =iferror(K42/D42,"") | M42: =IF($C$3="Load",iferror($B42*DVH($C$5,"totaldebt",$C42),"")-iferror($B42*DVH($C$5,"cash",$C42),""),M42) -> 0 | N42: =iferror(M42/F42,"") | O42: =IF($C$3="Load",DVH($C$5,"Shares",$C42),O42) -> No data available for | P42: =IF($C$3="Load",DVH($C$5,"MarketCap",$C42),P42) -> No data available for | Q42: =IF($C$3="Load",DVH($C$5,"EnterpriseValue",$C42),Q42) -> No data available for | R42: =iferror(K42/P42,"") | S42: =iferror(Q42/F42,"") | T42: =IF($C$3="Load",$B42*DVH($C$5,"TangibleBookValue",$C42),T42) -> #VALUE! | V42: =iferror(IF($C$3="Load",DVH($C$5,"grossprofit",$C42)*$B42,V42),"") | W42: =iferror(V42/$D42,"") | X42: =iferror(IF($C$3="Load",DVH($C$5,"netincome",$C42)*$B42,X42),"") | Y42: =iferror(X42/$D42,"") | Z42: =iferror(if(X42<0,if(F42<0,0,F42),if(F42>X42,(F42-X42),0)),"") | AA42: =iferror(if(and(X42<0,F42<0),V42,V42-max(F42,X42)),"") | AB42: =iferror(D42-V42,"")
A43: 2016 | B43: {=INDEX('Currency Conversion'!$C$4:$L$23, MATCH(C43, 'Currency Conversion'!$B$4:$B$23, 0), MATCH($E$16, 'Currency Conversion'!$C$3:$L$3, 0))} -> 1 | C43: 2016 | D43: =IF($C$3="Load",DVH($C$5,"revenue",$C43)*$B43,D43) -> #VALUE! | E43: =iferror(D43/D42-1,"") | F43: =IF($C$3="Load",DVH($C$5,"operatingincome",$C43)*$B43,F43) -> #VALUE! | G43: =iferror(F43/D43,"") | H43: =IF($C$3="Load",DVH($C$5,"operatingcashflow",$C43)*$B43,H43) -> #VALUE! | I43: =IF($C$3="Load",iferror(DVH($C$5,"capex",$C43)*$B43,""),I43) | J43: =IF($C$3="Load",iferror(DVH($C$5,"sharebasedcompensation",$C43)*$B43,""),J43) | K43: =iferror(H43-I43-J43,"") | L43: =iferror(K43/D43,"") | M43: =IF($C$3="Load",iferror($B43*DVH($C$5,"totaldebt",$C43),"")-iferror($B43*DVH($C$5,"cash",$C43),""),M43) -> 0 | N43: =iferror(M43/F43,"") | O43: =IF($C$3="Load",DVH($C$5,"Shares",$C43),O43) -> No data available for | P43: =IF($C$3="Load",DVH($C$5,"MarketCap",$C43),P43) -> No data available for | Q43: =IF($C$3="Load",DVH($C$5,"EnterpriseValue",$C43),Q43) -> No data available for | R43: =iferror(K43/P43,"") | S43: =iferror(Q43/F43,"") | T43: =IF($C$3="Load",$B43*DVH($C$5,"TangibleBookValue",$C43),T43) -> #VALUE! | V43: =iferror(IF($C$3="Load",DVH($C$5,"grossprofit",$C43)*$B43,V43),"") | W43: =iferror(V43/$D43,"") | X43: =iferror(IF($C$3="Load",DVH($C$5,"netincome",$C43)*$B43,X43),"") | Y43: =iferror(X43/$D43,"") | Z43: =iferror(if(X43<0,if(F43<0,0,F43),if(F43>X43,(F43-X43),0)),"") | AA43: =iferror(if(and(X43<0,F43<0),V43,V43-max(F43,X43)),"") | AB43: =iferror(D43-V43,"")
A44: 2017 | B44: {=INDEX('Currency Conversion'!$C$4:$L$23, MATCH(C44, 'Currency Conversion'!$B$4:$B$23, 0), MATCH($E$16, 'Currency Conversion'!$C$3:$L$3, 0))} -> 1 | C44: 2017 | D44: =IF($C$3="Load",DVH($C$5,"revenue",$C44)*$B44,D44) -> #VALUE! | E44: =iferror(D44/D43-1,"") | F44: =IF($C$3="Load",DVH($C$5,"operatingincome",$C44)*$B44,F44) -> #VALUE! | G44: =iferror(F44/D44,"") | H44: =IF($C$3="Load",DVH($C$5,"operatingcashflow",$C44)*$B44,H44) -> #VALUE! | I44: =IF($C$3="Load",iferror(DVH($C$5,"capex",$C44)*$B44,""),I44) | J44: =IF($C$3="Load",iferror(DVH($C$5,"sharebasedcompensation",$C44)*$B44,""),J44) | K44: =iferror(H44-I44-J44,"") | L44: =iferror(K44/D44,"") | M44: =IF($C$3="Load",iferror($B44*DVH($C$5,"totaldebt",$C44),"")-iferror($B44*DVH($C$5,"cash",$C44),""),M44) -> 0 | N44: =iferror(M44/F44,"") | O44: =IF($C$3="Load",DVH($C$5,"Shares",$C44),O44) -> No data available for | P44: =IF($C$3="Load",DVH($C$5,"MarketCap",$C44),P44) -> No data available for | Q44: =IF($C$3="Load",DVH($C$5,"EnterpriseValue",$C44),Q44) -> No data available for | R44: =iferror(K44/P44,"") | S44: =iferror(Q44/F44,"") | T44: =IF($C$3="Load",$B44*DVH($C$5,"TangibleBookValue",$C44),T44) -> #VALUE! | V44: =iferror(IF($C$3="Load",DVH($C$5,"grossprofit",$C44)*$B44,V44),"") | W44: =iferror(V44/$D44,"") | X44: =iferror(IF($C$3="Load",DVH($C$5,"netincome",$C44)*$B44,X44),"") | Y44: =iferror(X44/$D44,"") | Z44: =iferror(if(X44<0,if(F44<0,0,F44),if(F44>X44,(F44-X44),0)),"") | AA44: =iferror(if(and(X44<0,F44<0),V44,V44-max(F44,X44)),"") | AB44: =iferror(D44-V44,"")
A45: 2018 | B45: {=INDEX('Currency Conversion'!$C$4:$L$23, MATCH(C45, 'Currency Conversion'!$B$4:$B$23, 0), MATCH($E$16, 'Currency Conversion'!$C$3:$L$3, 0))} -> 1 | C45: 2018 | D45: =IF($C$3="Load",DVH($C$5,"revenue",$C45)*$B45,D45) -> #VALUE! | E45: =iferror(D45/D44-1,"") | F45: =IF($C$3="Load",DVH($C$5,"operatingincome",$C45)*$B45,F45) -> #VALUE! | G45: =iferror(F45/D45,"") | H45: =IF($C$3="Load",DVH($C$5,"operatingcashflow",$C45)*$B45,H45) -> #VALUE! | I45: =IF($C$3="Load",iferror(DVH($C$5,"capex",$C45)*$B45,""),I45) | J45: =IF($C$3="Load",iferror(DVH($C$5,"sharebasedcompensation",$C45)*$B45,""),J45) | K45: =iferror(H45-I45-J45,"") | L45: =iferror(K45/D45,"") | M45: =IF($C$3="Load",iferror($B45*DVH($C$5,"totaldebt",$C45),"")-iferror($B45*DVH($C$5,"cash",$C45),""),M45) -> 0 | N45: =iferror(M45/F45,"") | O45: =IF($C$3="Load",DVH($C$5,"Shares",$C45),O45) -> No data available for | P45: =IF($C$3="Load",DVH($C$5,"MarketCap",$C45),P45) -> No data available for | Q45: =IF($C$3="Load",DVH($C$5,"EnterpriseValue",$C45),Q45) -> No data available for | R45: =iferror(K45/P45,"") | S45: =iferror(Q45/F45,"") | T45: =IF($C$3="Load",$B45*DVH($C$5,"TangibleBookValue",$C45),T45) -> #VALUE! | V45: =iferror(IF($C$3="Load",DVH($C$5,"grossprofit",$C45)*$B45,V45),"") | W45: =iferror(V45/$D45,"") | X45: =iferror(IF($C$3="Load",DVH($C$5,"netincome",$C45)*$B45,X45),"") | Y45: =iferror(X45/$D45,"") | Z45: =iferror(if(X45<0,if(F45<0,0,F45),if(F45>X45,(F45-X45),0)),"") | AA45: =iferror(if(and(X45<0,F45<0),V45,V45-max(F45,X45)),"") | AB45: =iferror(D45-V45,"")
A46: 2019 | B46: {=INDEX('Currency Conversion'!$C$4:$L$23, MATCH(C46, 'Currency Conversion'!$B$4:$B$23, 0), MATCH($E$16, 'Currency Conversion'!$C$3:$L$3, 0))} -> 1 | C46: 2019 | D46: =IF($C$3="Load",DVH($C$5,"revenue",$C46)*$B46,D46) -> #VALUE! | E46: =iferror(D46/D45-1,"") | F46: =IF($C$3="Load",DVH($C$5,"operatingincome",$C46)*$B46,F46) -> #VALUE! | G46: =iferror(F46/D46,"") | H46: =IF($C$3="Load",DVH($C$5,"operatingcashflow",$C46)*$B46,H46) -> #VALUE! | I46: =IF($C$3="Load",iferror(DVH($C$5,"capex",$C46)*$B46,""),I46) | J46: =IF($C$3="Load",iferror(DVH($C$5,"sharebasedcompensation",$C46)*$B46,""),J46) | K46: =iferror(H46-I46-J46,"") | L46: =iferror(K46/D46,"") | M46: =IF($C$3="Load",iferror($B46*DVH($C$5,"totaldebt",$C46),"")-iferror($B46*DVH($C$5,"cash",$C46),""),M46) -> 0 | N46: =iferror(M46/F46,"") | O46: =IF($C$3="Load",DVH($C$5,"Shares",$C46),O46) -> No data available for | P46: =IF($C$3="Load",DVH($C$5,"MarketCap",$C46),P46) -> No data available for | Q46: =IF($C$3="Load",DVH($C$5,"EnterpriseValue",$C46),Q46) -> No data available for | R46: =iferror(K46/P46,"") | S46: =iferror(Q46/F46,"") | T46: =IF($C$3="Load",$B46*DVH($C$5,"TangibleBookValue",$C46),T46) -> #VALUE! | V46: =iferror(IF($C$3="Load",DVH($C$5,"grossprofit",$C46)*$B46,V46),"") | W46: =iferror(V46/$D46,"") | X46: =iferror(IF($C$3="Load",DVH($C$5,"netincome",$C46)*$B46,X46),"") | Y46: =iferror(X46/$D46,"") | Z46: =iferror(if(X46<0,if(F46<0,0,F46),if(F46>X46,(F46-X46),0)),"") | AA46: =iferror(if(and(X46<0,F46<0),V46,V46-max(F46,X46)),"") | AB46: =iferror(D46-V46,"")
... A52: 2024 | B52: {=INDEX('Currency Conversion'!$C$4:$L$23, MATCH(C52, 'Currency Conversion'!$B$4:$B$23, 0), MATCH($E$16, 'Currency Conversion'!$C$3:$L$3, 0))} -> 1 | C52: 2025 | D52: =IF($C$3="Load",DVH($C$5,"revenue",$C52)*$B52,D52) -> #VALUE! | E52: =iferror(D52/D51-1,"") | F52: =IF($C$3="Load",DVH($C$5,"operatingincome",$C52)*$B52,F52) -> #VALUE! | G52: =iferror(F52/D52,"") | H52: =IF($C$3="Load",DVH($C$5,"operatingcashflow",$C52)*$B52,H52) -> #VALUE! | I52: =IF($C$3="Load",iferror(DVH($C$5,"capex",$C52)*$B52,""),I52) | J52: =IF($C$3="Load",iferror(DVH($C$5,"sharebasedcompensation",$C52)*$B52,""),J52) | K52: =iferror(H52-I52-J52,"") | L52: =iferror(K52/D52,"") | M52: =IF($C$3="Load",iferror($B52*DVH($C$5,"totaldebt",$C52),"")-iferror($B52*DVH($C$5,"cash",$C52),""),M52) -> 0 | N52: =iferror(M52/F52,"") | O52: =IF($C$3="Load",DVH($C$5,"Shares",$C52),O52) -> No data available for | P52: =IF($C$3="Load",DVH($C$5,"MarketCap",$C52),P52) -> No data available for | Q52: =IF($C$3="Load",DVH($C$5,"EnterpriseValue",$C52),Q52) -> No data available for | R52: =iferror(K52/P52,"") | S52: =iferror(Q52/F52,"") | T52: =IF($C$3="Load",$B52*DVH($C$5,"TangibleBookValue",$C52),T52) -> #VALUE! | V52: =iferror(IF($C$3="Load",DVH($C$5,"grossprofit",$C52)*$B52,V52),"") | W52: =iferror(V52/$D52,"") | X52: =iferror(IF($C$3="Load",DVH($C$5,"netincome",$C52)*$B52,X52),"") | Y52: =iferror(X52/$D52,"") | Z52: =iferror(if(X52<0,if(F52<0,0,F52),if(F52>X52,(F52-X52),0)),"") | AA52: =iferror(if(and(X52<0,F52<0),V52,V52-max(F52,X52)),"") | AB52: =iferror(D52-V52,"")
A53: 2025 | B53: {=INDEX('Currency Conversion'!$C$4:$L$23, MATCH(C53, 'Currency Conversion'!$B$4:$B$23, 0), MATCH($E$16, 'Currency Conversion'!$C$3:$L$3, 0))} -> 1 | C53: TTM | D53: =IF($C$3="Load",DVH($C$5,"revenue",$C53)*$B53,D53) -> #VALUE! | E53: =iferror(D53/D51-1,"") | F53: =IF($C$3="Load",DVH($C$5,"operatingincome",$C53)*$B53,F53) -> #VALUE! | G53: =iferror(F53/D53,"") | H53: =IF($C$3="Load",DVH($C$5,"operatingcashflow",$C53)*$B53,H53) -> #VALUE! | I53: =IF($C$3="Load",iferror(DVH($C$5,"capex",$C53)*$B53,""),I53) | J53: =IF($C$3="Load",iferror(DVH($C$5,"sharebasedcompensation",$C53)*$B53,""),J53) | K53: =iferror(H53-I53-J53,"") | L53: =iferror(K53/D53,"") | M53: =IF($C$3="Load",iferror($B53*DVH($C$5,"totaldebt",$C53),"")-iferror($B53*DVH($C$5,"cash",$C53),""),M53) -> 0 | N53: =iferror(M53/F53,"") | O53: =IFERROR(__xludf.DUMMYFUNCTION("GOOGLEFINANCE($C$5,""shares"")"),"#N/A") -> #N/A | P53: =IFERROR(__xludf.DUMMYFUNCTION("GOOGLEFINANCE($C$5,""marketcap"")"),"#N/A") -> #N/A | Q53: =P53+M53 -> #N/A | R53: =iferror(K53/P53,"") | S53: =iferror(Q53/F53,"") | T53: =IF($C$3="Load",$B53*DVH($C$5,"TangibleBookValue",$C53),T53) -> #VALUE! | V53: =iferror(IF($C$3="Load",DVH($C$5,"grossprofit",$C53)*$B53,V53),"") | W53: =iferror(V53/$D53,"") | X53: =iferror(IF($C$3="Load",DVH($C$5,"netincome",$C53)*$B53,X53),"") | Y53: =iferror(X53/$D53,"") | Z53: =iferror(if(X53<0,if(F53<0,0,F53),if(F53>X53,(F53-X53),0)),"") | AA53: =iferror(if(and(X53<0,F53<0),V53,V53-max(F53,X53)),"") | AB53: =iferror(D53-V53,"") | AC53: =IFERROR(__xludf.DUMMYFUNCTION("IF($C$3=""Load"",GOOGLEFINANCE(C4,""price"",today()-7*365,today(),""weekly""),Arrayformula(AC53:AD449))"),"#N/A") -> #N/A
C54: CAGR or Avg | D54: =iferror((D51/D43)^(1/8)-1,"") | E54: =iferror(AVERAGE(E50:E53),"") | F54: =iferror((F51/F43)^(1/8)-1,"") | G54: =iferror(AVERAGE(G50:G53),"") | H54: =iferror((H51/H43)^(1/8)-1,"") | I54: =iferror((I51/I43)^(1/8)-1,"") | J54: =iferror((J51/J43)^(1/8)-1,"") | K54: =iferror((K51/K43)^(1/8)-1,"") | L54: =iferror(AVERAGE(L50:L53),"") | M54: =iferror((M51/M41)^(1/10)-1,"") | N54: =iferror(AVERAGE(N41:N53),"") | O54: =iferror((O51/O41)^(1/10)-1,"") | P54: =iferror((P51/P41)^(1/10)-1,"") | Q54: =iferror((Q51/Q41)^(1/10)-1,"") | R54: =iferror(TRIMMEAN(R41:R53,0.4),"") | S54: =iferror(TRIMMEAN(S41:S53,0.4),"") | T54: =iferror((T51/T41)^(1/10)-1,"")
D55: =IFERROR(__xludf.DUMMYFUNCTION("sparkline(D43:D53,{""charttype"",""column"";""color"",""0044CC"";""ymin"",min(D43:D53,0);""lastcolor"",""red""})"),"#VALUE!") -> #VALUE! | E55: =IFERROR(__xludf.DUMMYFUNCTION("sparkline(E43:E53,{""charttype"",""column"";""color"",""0044CC"";""ymin"",min(E43:E53,0);""lastcolor"",""red""})"),"#N/A") -> #N/A | F55: =IFERROR(__xludf.DUMMYFUNCTION("sparkline(F43:F53,{""charttype"",""column"";""color"",""0044CC"";""ymin"",min(F43:F53,0);""lastcolor"",""red""})"),"#VALUE!") -> #VALUE! | G55: =IFERROR(__xludf.DUMMYFUNCTION("sparkline(G43:G53,{""charttype"",""column"";""color"",""0044CC"";""ymin"",min(G43:G53,0);""lastcolor"",""red""})"),"#N/A") -> #N/A | H55: =IFERROR(__xludf.DUMMYFUNCTION("sparkline(H43:H53,{""charttype"",""column"";""color"",""0044CC"";""ymin"",min(H43:H53,0);""lastcolor"",""red""})"),"#VALUE!") -> #VALUE! | I55: =IFERROR(__xludf.DUMMYFUNCTION("sparkline(I43:I53,{""charttype"",""column"";""color"",""0044CC"";""ymin"",min(I43:I53,0);""lastcolor"",""red""})"),"#N/A") -> #N/A | J55: =IFERROR(__xludf.DUMMYFUNCTION("sparkline(J43:J53,{""charttype"",""column"";""color"",""0044CC"";""ymin"",min(J43:J53,0);""lastcolor"",""red""})"),"#N/A") -> #N/A | K55: =IFERROR(__xludf.DUMMYFUNCTION("sparkline(K43:K53,{""charttype"",""column"";""color"",""0044CC"";""ymin"",min(K43:K53,0);""lastcolor"",""red""})"),"#N/A") -> #N/A | L55: =IFERROR(__xludf.DUMMYFUNCTION("sparkline(L43:L53,{""charttype"",""column"";""color"",""0044CC"";""ymin"",min(L43:L53,0);""lastcolor"",""red""})"),"#N/A") -> #N/A | M55: =IFERROR(__xludf.DUMMYFUNCTION("sparkline(M43:M53,{""charttype"",""column"";""color"",""0044CC"";""ymin"",min(M43:M53,0);""lastcolor"",""red""})"),"") | N55: =IFERROR(__xludf.DUMMYFUNCTION("sparkline(N43:N53,{""charttype"",""column"";""color"",""0044CC"";""ymin"",min(N43:N53,0);""lastcolor"",""red""})"),"#N/A") -> #N/A | O55: =IFERROR(__xludf.DUMMYFUNCTION("sparkline(O43:O53,{""charttype"",""column"";""color"",""0044CC"";""ymin"",min(O43:O53,0);""lastcolor"",""red""})"),"#N/A") -> #N/A | P55: =IFERROR(__xludf.DUMMYFUNCTION("sparkline(P43:P53,{""charttype"",""column"";""color"",""0044CC"";""ymin"",min(P43:P53,0);""lastcolor"",""red""})"),"#N/A") -> #N/A | Q55: =IFERROR(__xludf.DUMMYFUNCTION("sparkline(Q43:Q53,{""charttype"",""column"";""color"",""0044CC"";""ymin"",min(Q43:Q53,0);""lastcolor"",""red""})"),"#N/A") -> #N/A | R55: =IFERROR(__xludf.DUMMYFUNCTION("sparkline(R43:R53,{""charttype"",""column"";""color"",""0044CC"";""ymin"",min(R43:R53,0);""lastcolor"",""red""})"),"#N/A") -> #N/A | S55: =IFERROR(__xludf.DUMMYFUNCTION("sparkline(S43:S53,{""charttype"",""column"";""color"",""0044CC"";""ymin"",min(S43:S53,0);""lastcolor"",""red""})"),"#N/A") -> #N/A | T55: =IFERROR(__xludf.DUMMYFUNCTION("sparkline(T43:T53,{""charttype"",""column"";""color"",""0044CC"";""ymin"",min(T43:T53,0);""lastcolor"",""red""})"),"#VALUE!") -> #VALUE!
C56: 1
C60: 5-year 2030 Forecasted Data
D61: Revenue | E61: Revenue Y/Y ∆ | F61: Operating Income | G61: Operating Margin | H61: Adj. FCF Margin | I61: Adj. FCF | J61: PV of Adj. FCF | K61: 2029 EV/EBIT Multiple | N61: =S53 | P61: IRR | Q61: {=if(countif(G63:H67,"=0")=10,"NA",IRR({-1*P$53,I63,I64,I65,I66,I67+N65}))} -> #N/A | R61: =IFERROR(Q61-0.03,) | S61: – | T61: =IFERROR(Q61+0.02,) | V61: s
K62: 2029 Enterprise Value | N62: =F67*N61 -> #VALUE! | R62: Base Case
C63: 2026 | D63: =D$53*(1+E63) -> #VALUE! | E63: =E53 | F63: =G63*D63 -> #VALUE! | G63: =G53 | H63: =L53 | I63: =H63*D63 -> #VALUE! | J63: =I63/(1+N$66)^(C63-C$63+1) -> #VALUE! | K63: Net Debt | N63: =M$53 -> 0 | P63: Fair Value Today | Q63: =if(Q61="NA","-",(N67/P$53)*I$6) -> #N/A
C64: =C63+1 -> 2027 | D64: =D63*(1+E64) -> #VALUE! | E64: =E63 | F64: =G64*D64 -> #VALUE! | G64: =G63 | H64: =H63 | I64: =H64*D64 -> #VALUE! | J64: =I64/(1+N$66)^(C64-C$63+1) -> #VALUE! | K64: Adjustment | N64: 0 | R64: =IFERROR(Q63-(Q63*0.05),) | S64: – | T64: =IFERROR(Q63+(Q63*0.05),)
C65: =C64+1 -> 2028 | D65: =D64*(1+E65) -> #VALUE! | E65: =E64 | F65: =G65*D65 -> #VALUE! | G65: =G64 | H65: =H64 | I65: =H65*D65 -> #VALUE! | J65: =I65/(1+N$66)^(C65-C$63+1) -> #VALUE! | K65: 2029 Market Cap | N65: =N62-N63+N64*1000000 -> #VALUE!
C66: =C65+1 -> 2029 | D66: =D65*(1+E66) -> #VALUE! | E66: =E65-1% -> -0.01 | F66: =G66*D66 -> #VALUE! | G66: =G65 | H66: =H65 | I66: =H66*D66 -> #VALUE! | J66: =I66/(1+N$66)^(C66-C$63+1) -> #VALUE! | K66: Discount Rate | N66: 0.1 | P66: 5-Yr Price Change | Q66: {=if(Q61="NA","-",(npv(Q61,I63:I66,I67)*(1+Q61)^5+N65)/P$53-1)} -> #N/A
C67: =C66+1 -> 2030 | D67: =D66*(1+E67) -> #VALUE! | E67: =E66-1% -> -0.02 | F67: =G67*D67 -> #VALUE! | G67: =G66 | H67: =H66 | I67: =H67*D67 -> #VALUE! | J67: =I67/(1+N$66)^(C67-C$63+1) -> #VALUE! | K67: PV of 2029 Market Cap + FCF | N67: =sum(J63:J67)+PV(N66,5,0,-1*N65) -> #VALUE! | R67: =IF(Q66=0,Q66-0.03,) -> #N/A | S67: – | T67: =IF(Q66=0,Q66+0.02,) -> #N/A
D69: Revenue | E69: Revenue Y/Y ∆ | F69: Operating Income | G69: Operating Margin | H69: Adj. FCF Margin | I69: Adj. FCF | J69: PV of Adj. FCF | K69: 2029 EV/EBIT Multiple | N69: 0 | P69: IRR | Q69: {=if(countif(G71:H75,"=0")=10,"NA",IRR({-1*P$53,I71,I72,I73,I74,I75+N73}))} -> NA | R69: =IFERROR(Q69-0.03,) | S69: – | T69: =IFERROR(Q69+0.02,)
K70: 2029 Enterprise Value | N70: =F75*N69 -> #VALUE! | R70: Bear Case
C71: =C63 -> 2026 | D71: =D$53*(1+E71) -> #VALUE! | E71: 0 | F71: =G71*D71 -> #VALUE! | G71: 0 | H71: 0 | I71: =H71*D71 -> #VALUE! | J71: =I71/(1+N$74)^(C71-C$71+1) -> #VALUE! | K71: Net Debt | N71: =M$53 -> 0 | P71: Fair Value Today | Q71: =if(Q69="NA","-",(N75/P$53)*I$6) -> -
C72: =C64 -> 2027 | D72: =D71*(1+E72) -> #VALUE! | E72: =E71 -> 0 | F72: =G72*D72 -> #VALUE! | G72: =G71 -> 0 | H72: =H71 -> 0 | I72: =H72*D72 -> #VALUE! | J72: =I72/(1+N$74)^(C72-C$71+1) -> #VALUE! | K72: Adjustment | N72: 0 | R72: =IFERROR(Q71-(Q71*0.05),) | S72: – | T72: =IFERROR(Q71+(Q71*0.05),)
C73: =C65 -> 2028 | D73: =D72*(1+E73) -> #VALUE! | E73: =E72 -> 0 | F73: =G73*D73 -> #VALUE! | G73: =G72 -> 0 | H73: =H72 -> 0 | I73: =H73*D73 -> #VALUE! | J73: =I73/(1+N$74)^(C73-C$71+1) -> #VALUE! | K73: 2029 Market Cap | N73: =N70-N71+N72*1000000 -> #VALUE!
C74: =C66 -> 2029 | D74: =D73*(1+E74) -> #VALUE! | E74: =E73-1% -> -0.01 | F74: =G74*D74 -> #VALUE! | G74: =G73 -> 0 | H74: =H73 -> 0 | I74: =H74*D74 -> #VALUE! | J74: =I74/(1+N$74)^(C74-C$71+1) -> #VALUE! | K74: Discount Rate | N74: =N66 -> 0.1 | P74: 5-Yr Price Change | Q74: {=if(Q69="NA","-",(npv(Q69,I71:I74,I75)*(1+Q69)^5+N73)/P$53-1)} -> -
C75: =C67 -> 2030 | D75: =D74*(1+E75) -> #VALUE! | E75: =E74-1% -> -0.02 | F75: =G75*D75 -> #VALUE! | G75: =G74 -> 0 | H75: =H74 -> 0 | I75: =H75*D75 -> #VALUE! | J75: =I75/(1+N$74)^(C75-C$71+1) -> #VALUE! | K75: PV of 2029 Market Cap + FCF | N75: =sum(J71:J75)+PV(N74,5,0,-1*N73) -> #VALUE! | R75: =IF(Q74=0,Q74-0.03,) | S75: – | T75: =IF(Q74=0,Q74+0.02,)
D77: Revenue | E77: Revenue Y/Y ∆ | F77: Operating Income | G77: Operating Margin | H77: Adj. FCF Margin | I77: Adj. FCF | J77: PV of Adj. FCF | K77: 2029 EV/EBIT Multiple | N77: 0 | P77: IRR | Q77: {=if(countif(G79:H83,"=0")=10,"NA",IRR({-1*P$53,I79,I80,I81,I82,I83+N81}))} -> NA | R77: =IFERROR(Q77-0.03,) | S77: – | T77: =IFERROR(Q77+0.02,)
K78: 2029 Enterprise Value | N78: =F83*N77 -> #VALUE! | R78: Bull Case
C79: =C71 -> 2026 | D79: =D$53*(1+E79) -> #VALUE! | E79: 0 | F79: =G79*D79 -> #VALUE! | G79: 0 | H79: 0 | I79: =H79*D79 -> #VALUE! | J79: =I79/(1+N$82)^(C79-C$79+1) -> #VALUE! | K79: Net Debt | N79: =M$53 -> 0 | P79: Fair Value Today | Q79: =if(Q77="NA","-",(N83/P$53)*I$6) -> -
C80: =C72 -> 2027 | D80: =D79*(1+E80) -> #VALUE! | E80: =E79 -> 0 | F80: =G80*D80 -> #VALUE! | G80: =G79 -> 0 | H80: =H79 -> 0 | I80: =H80*D80 -> #VALUE! | J80: =I80/(1+N$82)^(C80-C$79+1) -> #VALUE! | K80: Adjustment | N80: 0 | R80: =IFERROR(Q79-(Q79*0.05),) | S80: – | T80: =IFERROR(Q79+(Q79*0.05),)
C81: =C73 -> 2028 | D81: =D80*(1+E81) -> #VALUE! | E81: =E80 -> 0 | F81: =G81*D81 -> #VALUE! | G81: =G80 -> 0 | H81: =H80 -> 0 | I81: =H81*D81 -> #VALUE! | J81: =I81/(1+N$82)^(C81-C$79+1) -> #VALUE! | K81: 2029 Market Cap | N81: =N78-N79+N80*1000000 -> #VALUE!
C82: =C74 -> 2029 | D82: =D81*(1+E82) -> #VALUE! | E82: =E81-1% -> -0.01 | F82: =G82*D82 -> #VALUE! | G82: =G81 -> 0 | H82: =H81 -> 0 | I82: =H82*D82 -> #VALUE! | J82: =I82/(1+N$82)^(C82-C$79+1) -> #VALUE! | K82: Discount Rate | N82: =N66 -> 0.1 | P82: 5-Yr Price Change | Q82: {=if(Q77="NA","-",(npv(Q77,I79:I82,I83)*(1+Q77)^5+N81)/P$53-1)} -> -
C83: =C75 -> 2030 | D83: =D82*(1+E83) -> #VALUE! | E83: =E82-1% -> -0.02 | F83: =G83*D83 -> #VALUE! | G83: =G82 -> 0 | H83: =H82 -> 0 | I83: =H83*D83 -> #VALUE! | J83: =I83/(1+N$82)^(C83-C$79+1) -> #VALUE! | K83: PV of 2029 Market Cap + FCF | N83: =sum(J79:J83)+PV(N82,5,0,-1*N81) -> #VALUE! | R83: =IF(Q82=0,Q82-0.03,) | S83: – | T83: =IF(Q82=0,Q82+0.02,)
C85: 3-year 2028 Forecasted Data
D86: Revenue | E86: Revenue Y/Y ∆ | F86: Operating Income | G86: Operating Margin | H86: Adj. FCF Margin | I86: Adj. FCF | J86: PV of Adj. FCF | K86: 2027 EV/EBIT Multiple | N86: =N61-2 -> -2 | P86: IRR | Q86: {=if(countif(G88:H90,"=0")=10,"NA",IRR({-1*P$53,I88,I89,I90+N90}))} -> #N/A | R86: =IFERROR(Q86-0.03,) | S86: – | T86: =IFERROR(Q86+0.02,) | V86: s
K87: 2027 Enterprise Value | N87: =F90*N86 -> #VALUE! | R87: Base Case
C88: =C79 -> 2026 | D88: =D$53*(1+E88) -> #VALUE! | E88: =E63 | F88: =G88*D88 -> #VALUE! | G88: =G63 | H88: =H63 | I88: =H88*D88 -> #VALUE! | J88: =I88/(1+N$66)^(C88-C$63+1) -> #VALUE! | K88: Net Debt | N88: =M$53 -> 0 | P88: Fair Value Today | Q88: =if(Q86="NA","-",(N92/P$53)*I$6) -> #N/A
C89: =C80 -> 2027 | D89: =D88*(1+E89) -> #VALUE! | E89: =E88-1% -> -0.01 | F89: =G89*D89 -> #VALUE! | G89: =G88 | H89: =H88 | I89: =H89*D89 -> #VALUE! | J89: =I89/(1+N$66)^(C89-C$63+1) -> #VALUE! | K89: Adjustment | N89: 0 | R89: =IFERROR(Q88-(Q88*0.05),) | S89: – | T89: =IFERROR(Q88+(Q88*0.05),)
C90: =C81 -> 2028 | D90: =D89*(1+E90) -> #VALUE! | E90: =E89-1% -> -0.02 | F90: =G90*D90 -> #VALUE! | G90: =G89 | H90: =H89 | I90: =H90*D90 -> #VALUE! | J90: =I90/(1+N$66)^(C90-C$63+1) -> #VALUE! | K90: 2027 Market Cap | N90: =N87-N88+N89*1000000 -> #VALUE!
K91: Discount Rate | N91: 0.1 | P91: 3-Yr Price Change | Q91: {=if(Q86="NA","-",(npv(Q86,I88:I89,I90)*(1+Q86)^3+N90)/P$53-1)} -> #N/A
K92: PV of 2027 Market Cap + FCF | N92: =sum(J88:J90)+PV(N91,5,0,-1*N90) -> #VALUE! | R92: =IF(Q91=0,Q91-0.03,) -> #N/A | S92: – | T92: =IF(Q91=0,Q91+0.02,) -> #N/A
D94: Revenue | E94: Revenue Y/Y ∆ | F94: Operating Income | G94: Operating Margin | H94: Adj. FCF Margin | I94: Adj. FCF | J94: PV of Adj. FCF | K94: 2027 EV/EBIT Multiple | N94: =N69-3 -> -3 | P94: IRR | Q94: {=if(countif(G96:H98,"=0")=10,"NA",IRR({-1*P$53,I96,I97,I98+N98}))} -> #N/A | R94: =IFERROR(Q94-0.03,) | S94: – | T94: =IFERROR(Q94+0.02,)
K95: 2027 Enterprise Value | N95: =F98*N94 -> #VALUE! | R95: Bear Case
C96: =C88 -> 2026 | D96: =D$53*(1+E96) -> #VALUE! | E96: =E71 -> 0 | F96: =G96*D96 -> #VALUE! | G96: =G71 -> 0 | H96: =H71 -> 0 | I96: =H96*D96 -> #VALUE! | J96: =I96/(1+N$74)^(C96-C$71+1) -> #VALUE! | K96: Net Debt | N96: =M$53 -> 0 | P96: Fair Value Today | Q96: =if(Q94="NA","-",(N100/P$53)*I$6) -> #N/A
C97: =C89 -> 2027 | D97: =D96*(1+E97) -> #VALUE! | E97: =E96-1% -> -0.01 | F97: =G97*D97 -> #VALUE! | G97: =G96 -> 0 | H97: =H96 -> 0 | I97: =H97*D97 -> #VALUE! | J97: =I97/(1+N$74)^(C97-C$71+1) -> #VALUE! | K97: Adjustment | N97: 0 | R97: =IFERROR(Q96-(Q96*0.05),) | S97: – | T97: =IFERROR(Q96+(Q96*0.05),)
C98: =C90 -> 2028 | D98: =D97*(1+E98) -> #VALUE! | E98: =E97-1% -> -0.02 | F98: =G98*D98 -> #VALUE! | G98: =G97 -> 0 | H98: =H97 -> 0 | I98: =H98*D98 -> #VALUE! | J98: =I98/(1+N$74)^(C98-C$71+1) -> #VALUE! | K98: 2027 Market Cap | N98: =N95-N96+N97*1000000 -> #VALUE!
K99: Discount Rate | N99: =N91 -> 0.1 | P99: 3-Yr Price Change | Q99: {=if(Q94="NA","-",(npv(Q94,I96:I97,I98)*(1+Q94)^3+N98)/P$53-1)} -> #N/A
K100: PV of 2027 Market Cap + FCF | N100: =sum(J96:J98)+PV(N99,5,0,-1*N98) -> #VALUE! | R100: =IF(Q99=0,Q99-0.03,) -> #N/A | S100: – | T100: =IF(Q99=0,Q99+0.02,) -> #N/A
D102: Revenue | E102: Revenue Y/Y ∆ | F102: Operating Income | G102: Operating Margin | H102: Adj. FCF Margin | I102: Adj. FCF | J102: PV of Adj. FCF | K102: 2027 EV/EBIT Multiple | N102: =N77-2 -> -2 | P102: IRR | Q102: {=if(countif(G104:H106,"=0")=10,"NA",IRR({-1*P$53,I104,I105,I106+N106}))} -> #N/A | R102: =IFERROR(Q102-0.03,) | S102: – | T102: =IFERROR(Q102+0.02,)
K103: 2027 Enterprise Value | N103: =F106*N102 -> #VALUE! | R103: Bull Case
C104: =C96 -> 2026 | D104: =D$53*(1+E104) -> #VALUE! | E104: =E79 -> 0 | F104: =G104*D104 -> #VALUE! | G104: =G79 -> 0 | H104: =H79 -> 0 | I104: =H104*D104 -> #VALUE! | J104: =I104/(1+N$82)^(C104-C$79+1) -> #VALUE! | K104: Net Debt | N104: =M$53 -> 0 | P104: Fair Value Today | Q104: =if(Q102="NA","-",(N108/P$53)*I$6) -> #N/A
C105: =C97 -> 2027 | D105: =D104*(1+E105) -> #VALUE! | E105: =E104-1% -> -0.01 | F105: =G105*D105 -> #VALUE! | G105: =G104 -> 0 | H105: =H104 -> 0 | I105: =H105*D105 -> #VALUE! | J105: =I105/(1+N$82)^(C105-C$79+1) -> #VALUE! | K105: Adjustment | N105: 0 | R105: =IFERROR(Q104-(Q104*0.05),) | S105: – | T105: =IFERROR(Q104+(Q104*0.05),)
C106: =C98 -> 2028 | D106: =D105*(1+E106) -> #VALUE! | E106: =E105-1% -> -0.02 | F106: =G106*D106 -> #VALUE! | G106: =G105 -> 0 | H106: =H105 -> 0 | I106: =H106*D106 -> #VALUE! | J106: =I106/(1+N$82)^(C106-C$79+1) -> #VALUE! | K106: 2027 Market Cap | N106: =N103-N104+N105*1000000 -> #VALUE!
K107: Discount Rate | N107: =N91 -> 0.1 | P107: 3-Yr Price Change | Q107: {=if(Q102="NA","-",(npv(Q102,I104:I105,I106)*(1+Q102)^3+N106)/P$53-1)} -> #N/A
K108: PV of 2027 Market Cap + FCF | N108: =sum(J104:J106)+PV(N107,5,0,-1*N106) -> #VALUE! | R108: =IF(Q107=0,Q107-0.03,) -> #N/A | S108: – | T108: =IF(Q107=0,Q107+0.02,) -> #N/A
C110: Questions to check yourself | P110: Analyst Ratings
C111: Can I understand the company? | N111: No | P111: Date | Q111: Action | R111: Analyst | S111: Rating | T111: Price Target
C112: Is revenue growing? Did you sanity check your revenue growth assumptions? | N112: No | P112: =IFERROR(__xludf.DUMMYFUNCTION("IF($C$3=""Static"",ARRAYFORMULA(P112:T116),if(ARRAY_CONSTRAIN(IMPORTHTML(""https://finviz.com/quote.ashx?t=""&C5,""table"",""11""),10,5)=""[Table]"", """",CHOOSEROWS(IMPORTHTML(""https://finviz.com/quote.ashx?t=""&C5,""table"",""11""),2,3,4,5,6)))"),"#REF!") -> #REF!
C113: Can I predict the earnings/cash flow? | N113: No
C114: Are current earnings/FCF normal, not inflated by temporary tailwinds? | N114: No
C115: Are the company's earnings independent of commodity prices? | N115: No
C116: Is the debt reasonable / is balance sheet healthy? | N116: No
C117: Do the maturities on the debt seem manageable? | N117: No | P117: =IFERROR(__xludf.DUMMYFUNCTION("IF($C$3=""Load"",(REGEXREPLACE(QUERY(IMPORTHTML(""https://finviz.com/quote.ashx?t=""&$C$4,""table"",""9""),""select Col10 where Col9 = 'Avg Volume' ""),""\D+"","""")/REGEXREPLACE(QUERY(IMPORTHTML(""https://finviz.com/quote.ashx?t=""&$C$4,""table"",""9""),"&"""select Col10 where Col9 = 'Shs Float' ""),""\D+"","""")),N116)"),"#REF!") -> #REF!
C118: Does the company put its shareholders first? | N118: No | P118: Other Metrics
C119: Does this company have a wide moat? Does this company have any moat? | N119: No | P119: EV/EBIT | Q119: =iferror(Q53/F53,"") | R119: Insider Ownership | T119: =IFERROR(__xludf.DUMMYFUNCTION("IF($C$3=""Load"",iferror(value(REGEXREPLACE(QUERY(IMPORTHTML(""https://finviz.com/quote.ashx?t=""&$C$5,""table"",""9""),""select Col8 where Col7 = 'Insider Own' ""),""\*"",""""))),T119)"),"")
C120: Has management been good allocators of capital? | N120: No | P120: P/E | Q120: =iferror(P53/X53,"") | R120: Insider Ownership Change | T120: =IFERROR(__xludf.DUMMYFUNCTION("IF($C$3=""Load"",iferror(value(REGEXREPLACE(QUERY(IMPORTHTML(""https://finviz.com/quote.ashx?t=""&$C$5,""table"",""9""),""select Col8 where Col7 = 'Insider Trans' ""),""\*"","""")),""-""),T120)"),"-") -> -
C121: Is the business safe from low cost overseas competition? | N121: No | P121: P/Tang. Book | Q121: =iferror(P53/T53,"") | R121: Institutional ownership | T121: =IFERROR(__xludf.DUMMYFUNCTION("IF($C$3=""Load"",iferror(value(REGEXREPLACE(QUERY(IMPORTHTML(""https://finviz.com/quote.ashx?t=""&$C$5,""table"",""9""),""select Col8 where Col7 = 'Inst Own' ""),""\*"",""""))),T121)"),"")
C122: Is this company Amazon/Google-proof? | N122: No | P122: P/Adj. OCF | Q122: =iferror(P53/(H53-J53),"") | R122: Short Interest | T122: =IFERROR(__xludf.DUMMYFUNCTION("IF($C$3=""Load"",iferror(REGEXREPLACE(QUERY(IMPORTHTML(""https://finviz.com/quote.ashx?t=""&$C$5,""table"",""9""),""select Col10 where Col9 = 'Short Float' ""),""\*"","""")),T122)"),"")
C123: Can you handle the ugly bear case? | N123: No | P123: P/Adj. FCF | Q123: =iferror(P53/K53,"") | R123: Avg Volume / Float | T123: =iferror((if(P117>1,P117/1000,P117)),"")
C124: Do you think the company is more likely to meet your base case than not? | N124: No | P124: Adj. ROIC | Q124: =iferror(if(Q121<0,"Neg Book",(F53/(T53+if(M53<0,0,M53)))),"") | R124: 1yr - 1m ∆ (Momentum) | T124: =IFERROR(__xludf.DUMMYFUNCTION("IF($C$3=""Update"",iferror((index(GOOGLEFINANCE(C5,""price"",today()-30),2,2)-index(GOOGLEFINANCE(C5,""price"",today()-365),2,2))/index(GOOGLEFINANCE(C5,""price"",today()-365),2,2)),T124)"),0.0) -> 0
E126: Price/Earnings | F126: Price/ Sales | G126: Price/ Cash Flow | H126: EV/ EBITDA | I126: Sales Growth | J126: Earnings Growth | K126: Price/ 2026 Sales | L126: Price/ 2026 Earnings

Sheet META
C1: Welcome to the Deep Value Hunter Stock Valuation Template!
C3: Static | E3: This sheet uses the DVH function from the Deep Value Hunter Add-On. Install the Extension from Extensions -> Add-Ons -> Get Add-Ons. Turn Iterative Calculation on in File -> Settings -> Calculation. Enter your ticker in C5 and switch C3 to "Load" to get data on your company! After data is loaded switch C3 to "Static" to lock the sheet. Use "Update" to refresh price data. Get more info at DeepValueHunter.com
C4: =C5 -> META
C5: META | F5: =IFERROR(__xludf.DUMMYFUNCTION("IF($C$3=""Load"",iferror(GOOGLEFINANCE($C$5,""name"")),F5)"),"Meta Platforms Inc") -> Meta Platforms Inc | I5: Price Today | R5: Fair Value | S5: IRR | T5: Price ∆
I6: =IFERROR(__xludf.DUMMYFUNCTION("IF($C$3=""Static"", I6, iferror(GOOGLEFINANCE($C$5)))"),631.48) -> 631.48 | Q6: Base Case | R6: =if(S6="No Forecast","",Q63) -> 1490.0751 | S6: =if(countif(G63:H67,"=0")=10,"No Forecast", iferror(Q61,"No Forecast")) -> 0.34080165 | T6: =if(S6="No Forecast","",R6/I$6-1) -> 1.3596553
Q7: Bear Case | R7: =if(S7="No Forecast","",Q71) | S7: =if(countif(G71:H75,"=0")=10,"No Forecast",iferror(Q69,"No Forecast")) -> No Forecast | T7: =if(S7="No Forecast","",R7/I$6-1)
C8: Last Update | D8: =IF($C$3="Static",D8,today()) -> 46213 | K8: 52 wk H | Q8: Bull Case | R8: =if(S8="No Forecast","",Q79) | S8: =if(countif(G79:H83,"=0")=10,"No Forecast",iferror(Q77,"No Forecast")) -> No Forecast | T8: =if(S8="No Forecast","",R8/I$6-1)
C9: Market cap | D9: =IFERROR(__xludf.DUMMYFUNCTION("IF($C$3=""Static"", D9, iferror(GOOGLEFINANCE($C$5,""marketcap"")))"),1.636079379597E12) -> 1636079379597 | K9: =IFERROR(__xludf.DUMMYFUNCTION("IF($C$3=""Load"",iferror(GOOGLEFINANCE($C$5,"""")),F5)"),"Meta Platforms Inc") -> Meta Platforms Inc
C10: P/E Ratio | E10: =IFERROR(D9/X53,"") -> 27.061421 | K10: 52 wk L | Q10: Margin of Safety | R10: 0.15 | S10: 0.2 | T10: 0.3
C11: EV / Operating Income | E11: =iferror(Q53/F53,"") -> 20.559476 | K11: =IFERROR(__xludf.DUMMYFUNCTION("IF($C$3=""Load"",iferror(GOOGLEFINANCE($C$5,"""")),F5)"),"Meta Platforms Inc") -> Meta Platforms Inc | Q11: Target Buy Price | R11: =$R6*(1-R10) -> 1266.5638 | S11: =$R6*(1-S10) -> 1192.0601 | T11: =$R6*(1-T10) -> 1043.0526
C12: Adj FCF Yield | E12: =iferror(K53/P53,"") -> 0.099191936
C13: Net Debt / Op Income | E13: =N53 -> 0.57668476
C14: Operating Margin | E14: =G53 -> 0.41437855 | L14: Base Case Implied IRR at Different Prices
C15: ROIC | E15: =IF($C$3="Load",if(DVH($C$5,C15)="Data not available",DVH($C$5,C15,2024),DVH($C$5,C15)),E15) -> 0.1795 | L15: =M15-(N15-M15) -> 379 | M15: =N15-(O15-N15) -> 442 | N15: =O15-(P15-O15) -> 505 | O15: =P15-(Q15-P15) -> 568 | P15: =round(I6,0) -> 631 | Q15: =P15+round($I6/10,0) -> 694 | R15: =Q15+Q15-P15 -> 757 | S15: =R15+R15-Q15 -> 820 | T15: =S15+S15-R15 -> 883
C16: Reporting Currency | E16: USD | L16: =iferror(IRR({-1*$P$53*(L15/$I$6),$I63,$I64,$I65,$I66,$I67+$N65}),"-") -> 0.52111142 | M16: =iferror(IRR({-1*$P$53*(M15/$I$6),$I63,$I64,$I65,$I66,$I67+$N65}),"-") -> 0.46308687 | N16: =iferror(IRR({-1*$P$53*(N15/$I$6),$I63,$I64,$I65,$I66,$I67+$N65}),"-") -> 0.41552813 | O16: =iferror(IRR({-1*$P$53*(O15/$I$6),$I63,$I64,$I65,$I66,$I67+$N65}),"-") -> 0.37547746 | P16: =iferror(IRR({-1*$P$53*(P15/$I$6),$I63,$I64,$I65,$I66,$I67+$N65}),"-") -> 0.34104597 | Q16: =iferror(IRR({-1*$P$53*(Q15/$I$6),$I63,$I64,$I65,$I66,$I67+$N65}),"-") -> 0.3109602 | R16: =iferror(IRR({-1*$P$53*(R15/$I$6),$I63,$I64,$I65,$I66,$I67+$N65}),"-") -> 0.28432433 | S16: =iferror(IRR({-1*$P$53*(S15/$I$6),$I63,$I64,$I65,$I66,$I67+$N65}),"-") -> 0.26048627 | T16: =iferror(IRR({-1*$P$53*(T15/$I$6),$I63,$I64,$I65,$I66,$I67+$N65}),"-") -> 0.23895782
F20: Bear Case | G20: Base Case | H20: Bull Case
F21: =R7 | G21: =R6 -> 1490.0751 | H21: =R8
F22: =I6 -> 631.48 | G22: =I6 -> 631.48 | H22: =I6 -> 631.48
B32: Reporting Currency | C32: =IF(E16<>"USD", "Historical Data (converted to USD from " & E16 & ")", "Historical Data") -> Historical Data
B33: =E16 -> USD | D33: Revenue ($M) | E33: Y/Y ∆ | F33: Operating Income | G33: Operating Margin | H33: Operating Cash Flow | I33: Capex | J33: SBC | K33: Adj. FCF | L33: Adj. FCF Margin | M33: Net Debt | N33: Net Debt / EBIT | O33: Shares | P33: Market Cap | Q33: EV | R33: Adj. FCF Yield | S33: EV/EBIT | T33: Tangible Book | V33: Gross Profit | W33: Gross Margin | X33: Net Income | Y33: Net Margin | Z33: Op Inc - Net Inc | AA33: Gr Profit - Op Inc | AB33: Rev - Gr Profit
A34: 2007 | B34: {=INDEX('Currency Conversion'!$C$4:$L$23, MATCH(C34, 'Currency Conversion'!$B$4:$B$23, 0), MATCH($E$16, 'Currency Conversion'!$C$3:$L$3, 0))} -> 1 | C34: 2007 | D34: =IF($C$3="Load",DVH($C$5,"revenue",$C34)*$B34,D34) -> 153000000 | F34: =IF($C$3="Load",DVH($C$5,"operatingincome",$C34)*$B34,F34) -> -124000000 | G34: =iferror(F34/D34,"") -> -0.81045752 | H34: =IF($C$3="Load",DVH($C$5,"operatingcashflow",$C34)*$B34,H34) -> 0 | I34: =IF($C$3="Load",iferror(DVH($C$5,"capex",$C34)*$B34,""),I34) -> 0 | J34: =IF($C$3="Load",iferror(DVH($C$5,"sharebasedcompensation",$C34)*$B34,""),J34) -> 0 | K34: =iferror(H34-I34-J34,"") -> 0 | L34: =iferror(K34/D34,"") -> 0 | M34: =IF($C$3="Load",iferror($B34*DVH($C$5,"totaldebt",$C34),"")-iferror($B34*DVH($C$5,"cash",$C34),""),M34) -> 0 | N34: =iferror(M34/F34,"") -> 0 | O34: =IF($C$3="Load",DVH($C$5,"Shares",$C34),O34) -> 2138085036 | P34: =IF($C$3="Load",DVH($C$5,"MarketCap",$C34),P34) -> 81738990926 | Q34: =IF($C$3="Load",DVH($C$5,"EnterpriseValue",$C34),Q34) -> 0 | R34: =iferror(K34/P34,"") -> 0 | S34: =iferror(Q34/F34,"") -> 0 | T34: =IF($C$3="Load",$B34*DVH($C$5,"TangibleBookValue",$C34),T34) -> 0 | V34: =iferror(IF($C$3="Load",DVH($C$5,"grossprofit",$C34)*$B34,V34),"") -> 112000000 | W34: =iferror(V34/$D34,"") -> 0.73202614 | X34: =iferror(IF($C$3="Load",DVH($C$5,"netincome",$C34)*$B34,X34),"") -> -138000000 | Y34: =iferror(X34/$D34,"") -> -0.90196078 | Z34: =iferror(if(X34<0,if(F34<0,0,F34),if(F34>X34,(F34-X34),0)),"") -> 0 | AA34: =iferror(if(and(X34<0,F34<0),V34,V34-max(F34,X34)),"") -> 112000000 | AB34: =iferror(D34-V34,"") -> 41000000
A35: 2008 | B35: {=INDEX('Currency Conversion'!$C$4:$L$23, MATCH(C35, 'Currency Conversion'!$B$4:$B$23, 0), MATCH($E$16, 'Currency Conversion'!$C$3:$L$3, 0))} -> 1 | C35: 2008 | D35: =IF($C$3="Load",DVH($C$5,"revenue",$C35)*$B35,D35) -> 272000000 | E35: =iferror(D35/D34-1,"") -> 0.77777778 | F35: =IF($C$3="Load",DVH($C$5,"operatingincome",$C35)*$B35,F35) -> -55000000 | G35: =iferror(F35/D35,"") -> -0.20220588 | H35: =IF($C$3="Load",DVH($C$5,"operatingcashflow",$C35)*$B35,H35) -> 0 | I35: =IF($C$3="Load",iferror(DVH($C$5,"capex",$C35)*$B35,""),I35) -> 0 | J35: =IF($C$3="Load",iferror(DVH($C$5,"sharebasedcompensation",$C35)*$B35,""),J35) -> 0 | K35: =iferror(H35-I35-J35,"") -> 0 | L35: =iferror(K35/D35,"") -> 0 | M35: =IF($C$3="Load",iferror($B35*DVH($C$5,"totaldebt",$C35),"")-iferror($B35*DVH($C$5,"cash",$C35),""),M35) -> 0 | N35: =iferror(M35/F35,"") -> 0 | O35: =IF($C$3="Load",DVH($C$5,"Shares",$C35),O35) -> 2138085036 | P35: =IF($C$3="Load",DVH($C$5,"MarketCap",$C35),P35) -> 81738990926 | Q35: =IF($C$3="Load",DVH($C$5,"EnterpriseValue",$C35),Q35) -> 0 | R35: =iferror(K35/P35,"") -> 0 | S35: =iferror(Q35/F35,"") -> 0 | T35: =IF($C$3="Load",$B35*DVH($C$5,"TangibleBookValue",$C35),T35) -> 0 | V35: =iferror(IF($C$3="Load",DVH($C$5,"grossprofit",$C35)*$B35,V35),"") -> 148000000 | W35: =iferror(V35/$D35,"") -> 0.54411765 | X35: =iferror(IF($C$3="Load",DVH($C$5,"netincome",$C35)*$B35,X35),"") -> -56000000 | Y35: =iferror(X35/$D35,"") -> -0.20588235 | Z35: =iferror(if(X35<0,if(F35<0,0,F35),if(F35>X35,(F35-X35),0)),"") -> 0 | AA35: =iferror(if(and(X35<0,F35<0),V35,V35-max(F35,X35)),"") -> 148000000 | AB35: =iferror(D35-V35,"") -> 124000000
A36: 2009 | B36: {=INDEX('Currency Conversion'!$C$4:$L$23, MATCH(C36, 'Currency Conversion'!$B$4:$B$23, 0), MATCH($E$16, 'Currency Conversion'!$C$3:$L$3, 0))} -> 1 | C36: 2009 | D36: =IF($C$3="Load",DVH($C$5,"revenue",$C36)*$B36,D36) -> 777000000 | E36: =iferror(D36/D35-1,"") -> 1.8566176 | F36: =IF($C$3="Load",DVH($C$5,"operatingincome",$C36)*$B36,F36) -> 262000000 | G36: =iferror(F36/D36,"") -> 0.33719434 | H36: =IF($C$3="Load",DVH($C$5,"operatingcashflow",$C36)*$B36,H36) -> 155000000 | I36: =IF($C$3="Load",iferror(DVH($C$5,"capex",$C36)*$B36,""),I36) -> -33000000 | J36: =IF($C$3="Load",iferror(DVH($C$5,"sharebasedcompensation",$C36)*$B36,""),J36) -> 0 | K36: =iferror(H36-I36-J36,"") -> 188000000 | L36: =iferror(K36/D36,"") -> 0.24195624 | M36: =IF($C$3="Load",iferror($B36*DVH($C$5,"totaldebt",$C36),"")-iferror($B36*DVH($C$5,"cash",$C36),""),M36) -> 0 | N36: =iferror(M36/F36,"") -> 0 | O36: =IF($C$3="Load",DVH($C$5,"Shares",$C36),O36) -> 2138085036 | P36: =IF($C$3="Load",DVH($C$5,"MarketCap",$C36),P36) -> 81738990926 | Q36: =IF($C$3="Load",DVH($C$5,"EnterpriseValue",$C36),Q36) -> 0 | R36: =iferror(K36/P36,"") -> 0.0023000039 | S36: =iferror(Q36/F36,"") -> 0 | T36: =IF($C$3="Load",$B36*DVH($C$5,"TangibleBookValue",$C36),T36) -> 0 | V36: =iferror(IF($C$3="Load",DVH($C$5,"grossprofit",$C36)*$B36,V36),"") -> 554000000 | W36: =iferror(V36/$D36,"") -> 0.71299871 | X36: =iferror(IF($C$3="Load",DVH($C$5,"netincome",$C36)*$B36,X36),"") -> 122000000 | Y36: =iferror(X36/$D36,"") -> 0.15701416 | Z36: =iferror(if(X36<0,if(F36<0,0,F36),if(F36>X36,(F36-X36),0)),"") -> 140000000 | AA36: =iferror(if(and(X36<0,F36<0),V36,V36-max(F36,X36)),"") -> 292000000 | AB36: =iferror(D36-V36,"") -> 223000000
A37: 2010 | B37: {=INDEX('Currency Conversion'!$C$4:$L$23, MATCH(C37, 'Currency Conversion'!$B$4:$B$23, 0), MATCH($E$16, 'Currency Conversion'!$C$3:$L$3, 0))} -> 1 | C37: 2010 | D37: =IF($C$3="Load",DVH($C$5,"revenue",$C37)*$B37,D37) -> 1974000000 | E37: =iferror(D37/D36-1,"") -> 1.5405405 | F37: =IF($C$3="Load",DVH($C$5,"operatingincome",$C37)*$B37,F37) -> 1032000000 | G37: =iferror(F37/D37,"") -> 0.52279635 | H37: =IF($C$3="Load",DVH($C$5,"operatingcashflow",$C37)*$B37,H37) -> 698000000 | I37: =IF($C$3="Load",iferror(DVH($C$5,"capex",$C37)*$B37,""),I37) -> -293000000 | J37: =IF($C$3="Load",iferror(DVH($C$5,"sharebasedcompensation",$C37)*$B37,""),J37) -> 20000000 | K37: =iferror(H37-I37-J37,"") -> 971000000 | L37: =iferror(K37/D37,"") -> 0.49189463 | M37: =IF($C$3="Load",iferror($B37*DVH($C$5,"totaldebt",$C37),"")-iferror($B37*DVH($C$5,"cash",$C37),""),M37) -> -1312000000 | N37: =iferror(M37/F37,"") -> -1.2713178 | O37: =IF($C$3="Load",DVH($C$5,"Shares",$C37),O37) -> 2347042528 | P37: =IF($C$3="Load",DVH($C$5,"MarketCap",$C37),P37) -> 87815935845 | Q37: =IF($C$3="Load",DVH($C$5,"EnterpriseValue",$C37),Q37) -> 86503935845 | R37: =iferror(K37/P37,"") -> 0.011057219 | S37: =iferror(Q37/F37,"") -> 83.821643 | T37: =IF($C$3="Load",$B37*DVH($C$5,"TangibleBookValue",$C37),T37) -> 2066000000 | V37: =iferror(IF($C$3="Load",DVH($C$5,"grossprofit",$C37)*$B37,V37),"") -> 1481000000 | W37: =iferror(V37/$D37,"") -> 0.75025329 | X37: =iferror(IF($C$3="Load",DVH($C$5,"netincome",$C37)*$B37,X37),"") -> 372000000 | Y37: =iferror(X37/$D37,"") -> 0.18844985 | Z37: =iferror(if(X37<0,if(F37<0,0,F37),if(F37>X37,(F37-X37),0)),"") -> 660000000 | AA37: =iferror(if(and(X37<0,F37<0),V37,V37-max(F37,X37)),"") -> 449000000 | AB37: =iferror(D37-V37,"") -> 493000000
A38: 2011 | B38: {=INDEX('Currency Conversion'!$C$4:$L$23, MATCH(C38, 'Currency Conversion'!$B$4:$B$23, 0), MATCH($E$16, 'Currency Conversion'!$C$3:$L$3, 0))} -> 1 | C38: 2011 | D38: =IF($C$3="Load",DVH($C$5,"revenue",$C38)*$B38,D38) -> 3711000000 | E38: =iferror(D38/D37-1,"") -> 0.87993921 | F38: =IF($C$3="Load",DVH($C$5,"operatingincome",$C38)*$B38,F38) -> 1756000000 | G38: =iferror(F38/D38,"") -> 0.47318782 | H38: =IF($C$3="Load",DVH($C$5,"operatingcashflow",$C38)*$B38,H38) -> 1549000000 | I38: =IF($C$3="Load",iferror(DVH($C$5,"capex",$C38)*$B38,""),I38) -> -606000000 | J38: =IF($C$3="Load",iferror(DVH($C$5,"sharebasedcompensation",$C38)*$B38,""),J38) -> 217000000 | K38: =iferror(H38-I38-J38,"") -> 1938000000 | L38: =iferror(K38/D38,"") -> 0.5222312 | M38: =IF($C$3="Load",iferror($B38*DVH($C$5,"totaldebt",$C38),"")-iferror($B38*DVH($C$5,"cash",$C38),""),M38) -> -835000000 | N38: =iferror(M38/F38,"") -> -0.47551253 | O38: =IF($C$3="Load",DVH($C$5,"Shares",$C38),O38) -> 2347042529 | P38: =IF($C$3="Load",DVH($C$5,"MarketCap",$C38),P38) -> 87815935845 | Q38: =IF($C$3="Load",DVH($C$5,"EnterpriseValue",$C38),Q38) -> 86980935845 | R38: =iferror(K38/P38,"") -> 0.022068887 | S38: =iferror(Q38/F38,"") -> 49.533563 | T38: =IF($C$3="Load",$B38*DVH($C$5,"TangibleBookValue",$C38),T38) -> 4737000000 | V38: =iferror(IF($C$3="Load",DVH($C$5,"grossprofit",$C38)*$B38,V38),"") -> 2851000000 | W38: =iferror(V38/$D38,"") -> 0.76825653 | X38: =iferror(IF($C$3="Load",DVH($C$5,"netincome",$C38)*$B38,X38),"") -> 1000000000 | Y38: =iferror(X38/$D38,"") -> 0.26946915 | Z38: =iferror(if(X38<0,if(F38<0,0,F38),if(F38>X38,(F38-X38),0)),"") -> 756000000 | AA38: =iferror(if(and(X38<0,F38<0),V38,V38-max(F38,X38)),"") -> 1095000000 | AB38: =iferror(D38-V38,"") -> 860000000
A39: 2012 | B39: {=INDEX('Currency Conversion'!$C$4:$L$23, MATCH(C39, 'Currency Conversion'!$B$4:$B$23, 0), MATCH($E$16, 'Currency Conversion'!$C$3:$L$3, 0))} -> 1 | C39: 2012 | D39: =IF($C$3="Load",DVH($C$5,"revenue",$C39)*$B39,D39) -> 5089000000 | E39: =iferror(D39/D38-1,"") -> 0.37132848 | F39: =IF($C$3="Load",DVH($C$5,"operatingincome",$C39)*$B39,F39) -> 538000000 | G39: =iferror(F39/D39,"") -> 0.10571822 | H39: =IF($C$3="Load",DVH($C$5,"operatingcashflow",$C39)*$B39,H39) -> 1612000000 | I39: =IF($C$3="Load",iferror(DVH($C$5,"capex",$C39)*$B39,""),I39) -> -1235000000 | J39: =IF($C$3="Load",iferror(DVH($C$5,"sharebasedcompensation",$C39)*$B39,""),J39) -> 1572000000 | K39: =iferror(H39-I39-J39,"") -> 1275000000 | L39: =iferror(K39/D39,"") -> 0.25054038 | M39: =IF($C$3="Load",iferror($B39*DVH($C$5,"totaldebt",$C39),"")-iferror($B39*DVH($C$5,"cash",$C39),""),M39) -> -28000000 | N39: =iferror(M39/F39,"") -> -0.05204461 | O39: =IF($C$3="Load",DVH($C$5,"Shares",$C39),O39) -> 3200000000 | P39: =IF($C$3="Load",DVH($C$5,"MarketCap",$C39),P39) -> 85184000000 | Q39: =IF($C$3="Load",DVH($C$5,"EnterpriseValue",$C39),Q39) -> 85156000000 | R39: =iferror(K39/P39,"") -> 0.0149676 | S39: =iferror(Q39/F39,"") -> 158.28253 | T39: =IF($C$3="Load",$B39*DVH($C$5,"TangibleBookValue",$C39),T39) -> 10367000000 | V39: =iferror(IF($C$3="Load",DVH($C$5,"grossprofit",$C39)*$B39,V39),"") -> 3725000000 | W39: =iferror(V39/$D39,"") -> 0.73197092 | X39: =iferror(IF($C$3="Load",DVH($C$5,"netincome",$C39)*$B39,X39),"") -> 53000000 | Y39: =iferror(X39/$D39,"") -> 0.01041462 | Z39: =iferror(if(X39<0,if(F39<0,0,F39),if(F39>X39,(F39-X39),0)),"") -> 485000000 | AA39: =iferror(if(and(X39<0,F39<0),V39,V39-max(F39,X39)),"") -> 3187000000 | AB39: =iferror(D39-V39,"") -> 1364000000
A40: 2013 | B40: {=INDEX('Currency Conversion'!$C$4:$L$23, MATCH(C40, 'Currency Conversion'!$B$4:$B$23, 0), MATCH($E$16, 'Currency Conversion'!$C$3:$L$3, 0))} -> 1 | C40: 2013 | D40: =IF($C$3="Load",DVH($C$5,"revenue",$C40)*$B40,D40) -> 7872000000 | E40: =iferror(D40/D39-1,"") -> 0.54686579 | F40: =IF($C$3="Load",DVH($C$5,"operatingincome",$C40)*$B40,F40) -> 2804000000 | G40: =iferror(F40/D40,"") -> 0.35619919 | H40: =IF($C$3="Load",DVH($C$5,"operatingcashflow",$C40)*$B40,H40) -> 4222000000 | I40: =IF($C$3="Load",iferror(DVH($C$5,"capex",$C40)*$B40,""),I40) -> -1362000000 | J40: =IF($C$3="Load",iferror(DVH($C$5,"sharebasedcompensation",$C40)*$B40,""),J40) -> 906000000 | K40: =iferror(H40-I40-J40,"") -> 4678000000 | L40: =iferror(K40/D40,"") -> 0.59425813 | M40: =IF($C$3="Load",iferror($B40*DVH($C$5,"totaldebt",$C40),"")-iferror($B40*DVH($C$5,"cash",$C40),""),M40) -> -2847000000 | N40: =iferror(M40/F40,"") -> -1.0153352 | O40: =IF($C$3="Load",DVH($C$5,"Shares",$C40),O40) -> 2517000000 | P40: =IF($C$3="Load",DVH($C$5,"MarketCap",$C40),P40) -> 136728853362 | Q40: =IF($C$3="Load",DVH($C$5,"EnterpriseValue",$C40),Q40) -> 133881853362 | R40: =iferror(K40/P40,"") -> 0.0342137 | S40: =iferror(Q40/F40,"") -> 47.746738 | T40: =IF($C$3="Load",$B40*DVH($C$5,"TangibleBookValue",$C40),T40) -> 13748000000 | V40: =iferror(IF($C$3="Load",DVH($C$5,"grossprofit",$C40)*$B40,V40),"") -> 5997000000 | W40: =iferror(V40/$D40,"") -> 0.76181402 | X40: =iferror(IF($C$3="Load",DVH($C$5,"netincome",$C40)*$B40,X40),"") -> 1491000000 | Y40: =iferror(X40/$D40,"") -> 0.18940549 | Z40: =iferror(if(X40<0,if(F40<0,0,F40),if(F40>X40,(F40-X40),0)),"") -> 1313000000 | AA40: =iferror(if(and(X40<0,F40<0),V40,V40-max(F40,X40)),"") -> 3193000000 | AB40: =iferror(D40-V40,"") -> 1875000000
A41: 2014 | B41: {=INDEX('Currency Conversion'!$C$4:$L$23, MATCH(C41, 'Currency Conversion'!$B$4:$B$23, 0), MATCH($E$16, 'Currency Conversion'!$C$3:$L$3, 0))} -> 1 | C41: 2014 | D41: =IF($C$3="Load",DVH($C$5,"revenue",$C41)*$B41,D41) -> 12466000000 | E41: =iferror(D41/D40-1,"") -> 0.5835874 | F41: =IF($C$3="Load",DVH($C$5,"operatingincome",$C41)*$B41,F41) -> 4994000000 | G41: =iferror(F41/D41,"") -> 0.40060966 | H41: =IF($C$3="Load",DVH($C$5,"operatingcashflow",$C41)*$B41,H41) -> 5457000000 | I41: =IF($C$3="Load",iferror(DVH($C$5,"capex",$C41)*$B41,""),I41) -> -1831000000 | J41: =IF($C$3="Load",iferror(DVH($C$5,"sharebasedcompensation",$C41)*$B41,""),J41) -> 1786000000 | K41: =iferror(H41-I41-J41,"") -> 5502000000 | L41: =iferror(K41/D41,"") -> 0.4413605 | M41: =IF($C$3="Load",iferror($B41*DVH($C$5,"totaldebt",$C41),"")-iferror($B41*DVH($C$5,"cash",$C41),""),M41) -> -4082000000 | N41: =iferror(M41/F41,"") -> -0.81738086 | O41: =IF($C$3="Load",DVH($C$5,"Shares",$C41),O41) -> 2664000000 | P41: =IF($C$3="Load",DVH($C$5,"MarketCap",$C41),P41) -> 206784988200 | Q41: =IF($C$3="Load",DVH($C$5,"EnterpriseValue",$C41),Q41) -> 202702988200 | R41: =iferror(K41/P41,"") -> 0.026607347 | S41: =iferror(Q41/F41,"") -> 40.589305 | T41: =IF($C$3="Load",$B41*DVH($C$5,"TangibleBookValue",$C41),T41) -> 14186000000 | V41: =iferror(IF($C$3="Load",DVH($C$5,"grossprofit",$C41)*$B41,V41),"") -> 10313000000 | W41: =iferror(V41/$D41,"") -> 0.82729023 | X41: =iferror(IF($C$3="Load",DVH($C$5,"netincome",$C41)*$B41,X41),"") -> 2940000000 | Y41: =iferror(X41/$D41,"") -> 0.23584149 | Z41: =iferror(if(X41<0,if(F41<0,0,F41),if(F41>X41,(F41-X41),0)),"") -> 2054000000 | AA41: =iferror(if(and(X41<0,F41<0),V41,V41-max(F41,X41)),"") -> 5319000000 | AB41: =iferror(D41-V41,"") -> 2153000000
A42: 2015 | B42: {=INDEX('Currency Conversion'!$C$4:$L$23, MATCH(C42, 'Currency Conversion'!$B$4:$B$23, 0), MATCH($E$16, 'Currency Conversion'!$C$3:$L$3, 0))} -> 1 | C42: 2015 | D42: =IF($C$3="Load",DVH($C$5,"revenue",$C42)*$B42,D42) -> 17928000000 | E42: =iferror(D42/D41-1,"") -> 0.43815177 | F42: =IF($C$3="Load",DVH($C$5,"operatingincome",$C42)*$B42,F42) -> 6225000000 | G42: =iferror(F42/D42,"") -> 0.34722222 | H42: =IF($C$3="Load",DVH($C$5,"operatingcashflow",$C42)*$B42,H42) -> 8599000000 | I42: =IF($C$3="Load",iferror(DVH($C$5,"capex",$C42)*$B42,""),I42) -> -2523000000 | J42: =IF($C$3="Load",iferror(DVH($C$5,"sharebasedcompensation",$C42)*$B42,""),J42) -> 2960000000 | K42: =iferror(H42-I42-J42,"") -> 8162000000 | L42: =iferror(K42/D42,"") -> 0.45526551 | M42: =IF($C$3="Load",iferror($B42*DVH($C$5,"totaldebt",$C42),"")-iferror($B42*DVH($C$5,"cash",$C42),""),M42) -> -4592000000 | N42: =iferror(M42/F42,"") -> -0.73767068 | O42: =IF($C$3="Load",DVH($C$5,"Shares",$C42),O42) -> 2853000000 | P42: =IF($C$3="Load",DVH($C$5,"MarketCap",$C42),P42) -> 297056791980 | Q42: =IF($C$3="Load",DVH($C$5,"EnterpriseValue",$C42),Q42) -> 292464791980 | R42: =iferror(K42/P42,"") -> 0.027476228 | S42: =iferror(Q42/F42,"") -> 46.982296 | T42: =IF($C$3="Load",$B42*DVH($C$5,"TangibleBookValue",$C42),T42) -> 22946000000 | V42: =iferror(IF($C$3="Load",DVH($C$5,"grossprofit",$C42)*$B42,V42),"") -> 15061000000 | W42: =iferror(V42/$D42,"") -> 0.84008255 | X42: =iferror(IF($C$3="Load",DVH($C$5,"netincome",$C42)*$B42,X42),"") -> 3688000000 | Y42: =iferror(X42/$D42,"") -> 0.20571174 | Z42: =iferror(if(X42<0,if(F42<0,0,F42),if(F42>X42,(F42-X42),0)),"") -> 2537000000 | AA42: =iferror(if(and(X42<0,F42<0),V42,V42-max(F42,X42)),"") -> 8836000000 | AB42: =iferror(D42-V42,"") -> 2867000000
A43: 2016 | B43: {=INDEX('Currency Conversion'!$C$4:$L$23, MATCH(C43, 'Currency Conversion'!$B$4:$B$23, 0), MATCH($E$16, 'Currency Conversion'!$C$3:$L$3, 0))} -> 1 | C43: 2016 | D43: =IF($C$3="Load",DVH($C$5,"revenue",$C43)*$B43,D43) -> 27638000000 | E43: =iferror(D43/D42-1,"") -> 0.54161089 | F43: =IF($C$3="Load",DVH($C$5,"operatingincome",$C43)*$B43,F43) -> 12427000000 | G43: =iferror(F43/D43,"") -> 0.44963456 | H43: =IF($C$3="Load",DVH($C$5,"operatingcashflow",$C43)*$B43,H43) -> 16108000000 | I43: =IF($C$3="Load",iferror(DVH($C$5,"capex",$C43)*$B43,""),I43) -> -4491000000 | J43: =IF($C$3="Load",iferror(DVH($C$5,"sharebasedcompensation",$C43)*$B43,""),J43) -> 3218000000 | K43: =iferror(H43-I43-J43,"") -> 17381000000 | L43: =iferror(K43/D43,"") -> 0.62888053 | M43: =IF($C$3="Load",iferror($B43*DVH($C$5,"totaldebt",$C43),"")-iferror($B43*DVH($C$5,"cash",$C43),""),M43) -> -8903000000 | N43: =iferror(M43/F43,"") -> -0.71642392 | O43: =IF($C$3="Load",DVH($C$5,"Shares",$C43),O43) -> 2925000000 | P43: =IF($C$3="Load",DVH($C$5,"MarketCap",$C43),P43) -> 335566104900 | Q43: =IF($C$3="Load",DVH($C$5,"EnterpriseValue",$C43),Q43) -> 326663104900 | R43: =iferror(K43/P43,"") -> 0.051796054 | S43: =iferror(Q43/F43,"") -> 26.286562 | T43: =IF($C$3="Load",$B43*DVH($C$5,"TangibleBookValue",$C43),T43) -> 38537000000 | V43: =iferror(IF($C$3="Load",DVH($C$5,"grossprofit",$C43)*$B43,V43),"") -> 23849000000 | W43: =iferror(V43/$D43,"") -> 0.86290614 | X43: =iferror(IF($C$3="Load",DVH($C$5,"netincome",$C43)*$B43,X43),"") -> 10188000000 | Y43: =iferror(X43/$D43,"") -> 0.36862291 | Z43: =iferror(if(X43<0,if(F43<0,0,F43),if(F43>X43,(F43-X43),0)),"") -> 2239000000 | AA43: =iferror(if(and(X43<0,F43<0),V43,V43-max(F43,X43)),"") -> 11422000000 | AB43: =iferror(D43-V43,"") -> 3789000000
A44: 2017 | B44: {=INDEX('Currency Conversion'!$C$4:$L$23, MATCH(C44, 'Currency Conversion'!$B$4:$B$23, 0), MATCH($E$16, 'Currency Conversion'!$C$3:$L$3, 0))} -> 1 | C44: 2017 | D44: =IF($C$3="Load",DVH($C$5,"revenue",$C44)*$B44,D44) -> 40653000000 | E44: =iferror(D44/D43-1,"") -> 0.47090962 | F44: =IF($C$3="Load",DVH($C$5,"operatingincome",$C44)*$B44,F44) -> 20203000000 | G44: =iferror(F44/D44,"") -> 0.49696209 | H44: =IF($C$3="Load",DVH($C$5,"operatingcashflow",$C44)*$B44,H44) -> 24216000000 | I44: =IF($C$3="Load",iferror(DVH($C$5,"capex",$C44)*$B44,""),I44) -> -6733000000 | J44: =IF($C$3="Load",iferror(DVH($C$5,"sharebasedcompensation",$C44)*$B44,""),J44) -> 3723000000 | K44: =iferror(H44-I44-J44,"") -> 27226000000 | L44: =iferror(K44/D44,"") -> 0.66971687 | M44: =IF($C$3="Load",iferror($B44*DVH($C$5,"totaldebt",$C44),"")-iferror($B44*DVH($C$5,"cash",$C44),""),M44) -> -7739000000 | N44: =iferror(M44/F44,"") -> -0.38306192 | O44: =IF($C$3="Load",DVH($C$5,"Shares",$C44),O44) -> 2956000000 | P44: =IF($C$3="Load",DVH($C$5,"MarketCap",$C44),P44) -> 521157493380 | Q44: =IF($C$3="Load",DVH($C$5,"EnterpriseValue",$C44),Q44) -> 513418493380 | R44: =iferror(K44/P44,"") -> 0.052241406 | S44: =iferror(Q44/F44,"") -> 25.412983 | T44: =IF($C$3="Load",$B44*DVH($C$5,"TangibleBookValue",$C44),T44) -> 54242000000 | V44: =iferror(IF($C$3="Load",DVH($C$5,"grossprofit",$C44)*$B44,V44),"") -> 35199000000 | W44: =iferror(V44/$D44,"") -> 0.86584016 | X44: =iferror(IF($C$3="Load",DVH($C$5,"netincome",$C44)*$B44,X44),"") -> 15920000000 | Y44: =iferror(X44/$D44,"") -> 0.39160702 | Z44: =iferror(if(X44<0,if(F44<0,0,F44),if(F44>X44,(F44-X44),0)),"") -> 4283000000 | AA44: =iferror(if(and(X44<0,F44<0),V44,V44-max(F44,X44)),"") -> 14996000000 | AB44: =iferror(D44-V44,"") -> 5454000000
A45: 2018 | B45: {=INDEX('Currency Conversion'!$C$4:$L$23, MATCH(C45, 'Currency Conversion'!$B$4:$B$23, 0), MATCH($E$16, 'Currency Conversion'!$C$3:$L$3, 0))} -> 1 | C45: 2018 | D45: =IF($C$3="Load",DVH($C$5,"revenue",$C45)*$B45,D45) -> 55838000000 | E45: =iferror(D45/D44-1,"") -> 0.37352717 | F45: =IF($C$3="Load",DVH($C$5,"operatingincome",$C45)*$B45,F45) -> 24913000000 | G45: =iferror(F45/D45,"") -> 0.44616569 | H45: =IF($C$3="Load",DVH($C$5,"operatingcashflow",$C45)*$B45,H45) -> 29274000000 | I45: =IF($C$3="Load",iferror(DVH($C$5,"capex",$C45)*$B45,""),I45) -> -13915000000 | J45: =IF($C$3="Load",iferror(DVH($C$5,"sharebasedcompensation",$C45)*$B45,""),J45) -> 4152000000 | K45: =iferror(H45-I45-J45,"") -> 39037000000 | L45: =iferror(K45/D45,"") -> 0.69911172 | M45: =IF($C$3="Load",iferror($B45*DVH($C$5,"totaldebt",$C45),"")-iferror($B45*DVH($C$5,"cash",$C45),""),M45) -> -9519000000 | N45: =iferror(M45/F45,"") -> -0.38208967 | O45: =IF($C$3="Load",DVH($C$5,"Shares",$C45),O45) -> 2921000000 | P45: =IF($C$3="Load",DVH($C$5,"MarketCap",$C45),P45) -> 378850100000 | Q45: =IF($C$3="Load",DVH($C$5,"EnterpriseValue",$C45),Q45) -> 369331100000 | R45: =iferror(K45/P45,"") -> 0.10304075 | S45: =iferror(Q45/F45,"") -> 14.824834 | T45: =IF($C$3="Load",$B45*DVH($C$5,"TangibleBookValue",$C45),T45) -> 64532000000 | V45: =iferror(IF($C$3="Load",DVH($C$5,"grossprofit",$C45)*$B45,V45),"") -> 46483000000 | W45: =iferror(V45/$D45,"") -> 0.83246176 | X45: =iferror(IF($C$3="Load",DVH($C$5,"netincome",$C45)*$B45,X45),"") -> 22112000000 | Y45: =iferror(X45/$D45,"") -> 0.39600272 | Z45: =iferror(if(X45<0,if(F45<0,0,F45),if(F45>X45,(F45-X45),0)),"") -> 2801000000 | AA45: =iferror(if(and(X45<0,F45<0),V45,V45-max(F45,X45)),"") -> 21570000000 | AB45: =iferror(D45-V45,"") -> 9355000000
A46: 2019 | B46: {=INDEX('Currency Conversion'!$C$4:$L$23, MATCH(C46, 'Currency Conversion'!$B$4:$B$23, 0), MATCH($E$16, 'Currency Conversion'!$C$3:$L$3, 0))} -> 1 | C46: 2019 | D46: =IF($C$3="Load",DVH($C$5,"revenue",$C46)*$B46,D46) -> 70697000000 | E46: =iferror(D46/D45-1,"") -> 0.2661091 | F46: =IF($C$3="Load",DVH($C$5,"operatingincome",$C46)*$B46,F46) -> 23986000000 | G46: =iferror(F46/D46,"") -> 0.33927889 | H46: =IF($C$3="Load",DVH($C$5,"operatingcashflow",$C46)*$B46,H46) -> 36314000000 | I46: =IF($C$3="Load",iferror(DVH($C$5,"capex",$C46)*$B46,""),I46) -> -15102000000 | J46: =IF($C$3="Load",iferror(DVH($C$5,"sharebasedcompensation",$C46)*$B46,""),J46) -> 4836000000 | K46: =iferror(H46-I46-J46,"") -> 46580000000 | L46: =iferror(K46/D46,"") -> 0.65886813 | M46: =IF($C$3="Load",iferror($B46*DVH($C$5,"totaldebt",$C46),"")-iferror($B46*DVH($C$5,"cash",$C46),""),M46) -> -8478000000 | N46: =iferror(M46/F46,"") -> -0.35345618 | O46: =IF($C$3="Load",DVH($C$5,"Shares",$C46),O46) -> 2876000000 | P46: =IF($C$3="Load",DVH($C$5,"MarketCap",$C46),P46) -> 585783500000 | Q46: =IF($C$3="Load",DVH($C$5,"EnterpriseValue",$C46),Q46) -> 577305500000 | R46: =iferror(K46/P46,"") -> 0.079517433 | S46: =iferror(Q46/F46,"") -> 24.068436 | T46: =IF($C$3="Load",$B46*DVH($C$5,"TangibleBookValue",$C46),T46) -> 81445000000 | V46: =iferror(IF($C$3="Load",DVH($C$5,"grossprofit",$C46)*$B46,V46),"") -> 57927000000 | W46: =iferror(V46/$D46,"") -> 0.81936999 | X46: =iferror(IF($C$3="Load",DVH($C$5,"netincome",$C46)*$B46,X46),"") -> 18485000000 | Y46: =iferror(X46/$D46,"") -> 0.26146795 | Z46: =iferror(if(X46<0,if(F46<0,0,F46),if(F46>X46,(F46-X46),0)),"") -> 5501000000 | AA46: =iferror(if(and(X46<0,F46<0),V46,V46-max(F46,X46)),"") -> 33941000000 | AB46: =iferror(D46-V46,"") -> 12770000000
... A52: 2024 | B52: {=INDEX('Currency Conversion'!$C$4:$L$23, MATCH(C52, 'Currency Conversion'!$B$4:$B$23, 0), MATCH($E$16, 'Currency Conversion'!$C$3:$L$3, 0))} -> 1 | C52: 2025 | D52: =IF($C$3="Load",DVH($C$5,"revenue",$C52)*$B52,D52) -> 200966000000 | E52: =iferror(D52/D51-1,"") -> 0.22167038 | F52: =IF($C$3="Load",DVH($C$5,"operatingincome",$C52)*$B52,F52) -> 83276000000 | G52: =iferror(F52/D52,"") -> 0.41437855 | H52: =IF($C$3="Load",DVH($C$5,"operatingcashflow",$C52)*$B52,H52) -> 115800000000 | I52: =IF($C$3="Load",iferror(DVH($C$5,"capex",$C52)*$B52,""),I52) -> -69691000000 | J52: =IF($C$3="Load",iferror(DVH($C$5,"sharebasedcompensation",$C52)*$B52,""),J52) -> 20427000000 | K52: =iferror(H52-I52-J52,"") -> 165064000000 | L52: =iferror(K52/D52,"") -> 0.82135287 | M52: =IF($C$3="Load",iferror($B52*DVH($C$5,"totaldebt",$C52),"")-iferror($B52*DVH($C$5,"cash",$C52),""),M52) -> 48024000000 | N52: =iferror(M52/F52,"") -> 0.57668476 | O52: =IF($C$3="Load",DVH($C$5,"Shares",$C52),O52) -> 2574000000 | P52: =IF($C$3="Load",DVH($C$5,"MarketCap",$C52),P52) -> 1664086890000 | Q52: =IF($C$3="Load",DVH($C$5,"EnterpriseValue",$C52),Q52) -> 1712110890000 | R52: =iferror(K52/P52,"") -> 0.099191936 | S52: =iferror(Q52/F52,"") -> 20.559476 | T52: =IF($C$3="Load",$B52*DVH($C$5,"TangibleBookValue",$C52),T52) -> 192709000000 | V52: =iferror(IF($C$3="Load",DVH($C$5,"grossprofit",$C52)*$B52,V52),"") -> 164791000000 | W52: =iferror(V52/$D52,"") -> 0.81999443 | X52: =iferror(IF($C$3="Load",DVH($C$5,"netincome",$C52)*$B52,X52),"") -> 60458000000 | Y52: =iferror(X52/$D52,"") -> 0.30083696 | Z52: =iferror(if(X52<0,if(F52<0,0,F52),if(F52>X52,(F52-X52),0)),"") -> 22818000000 | AA52: =iferror(if(and(X52<0,F52<0),V52,V52-max(F52,X52)),"") -> 81515000000 | AB52: =iferror(D52-V52,"") -> 36175000000
A53: 2025 | B53: {=INDEX('Currency Conversion'!$C$4:$L$23, MATCH(C53, 'Currency Conversion'!$B$4:$B$23, 0), MATCH($E$16, 'Currency Conversion'!$C$3:$L$3, 0))} -> 1 | C53: TTM | D53: =IF($C$3="Load",DVH($C$5,"revenue",$C53)*$B53,D53) -> 200966000000 | E53: =iferror(D53/D51-1,"") -> 0.22167038 | F53: =IF($C$3="Load",DVH($C$5,"operatingincome",$C53)*$B53,F53) -> 83276000000 | G53: =iferror(F53/D53,"") -> 0.41437855 | H53: =IF($C$3="Load",DVH($C$5,"operatingcashflow",$C53)*$B53,H53) -> 115800000000 | I53: =IF($C$3="Load",iferror(DVH($C$5,"capex",$C53)*$B53,""),I53) -> -69691000000 | J53: =IF($C$3="Load",iferror(DVH($C$5,"sharebasedcompensation",$C53)*$B53,""),J53) -> 20427000000 | K53: =iferror(H53-I53-J53,"") -> 165064000000 | L53: =iferror(K53/D53,"") -> 0.82135287 | M53: =IF($C$3="Load",iferror($B53*DVH($C$5,"totaldebt",$C53),"")-iferror($B53*DVH($C$5,"cash",$C53),""),M53) -> 48024000000 | N53: =iferror(M53/F53,"") -> 0.57668476 | O53: =IFERROR(__xludf.DUMMYFUNCTION("IF($C$3=""Static"", O52, GOOGLEFINANCE($C$5,""shares""))"),2.574E9) -> 2574000000 | P53: =IFERROR(__xludf.DUMMYFUNCTION("IF($C$3=""Static"", P52, GOOGLEFINANCE($C$5,""marketcap""))"),1.66408689E12) -> 1664086890000 | Q53: =P53+M53 -> 1712110890000 | R53: =iferror(K53/P53,"") -> 0.099191936 | S53: =iferror(Q53/F53,"") -> 20.559476 | T53: =IF($C$3="Load",$B53*DVH($C$5,"TangibleBookValue",$C53),T53) -> 192709000000 | V53: =iferror(IF($C$3="Load",DVH($C$5,"grossprofit",$C53)*$B53,V53),"") -> 164791000000 | W53: =iferror(V53/$D53,"") -> 0.81999443 | X53: =iferror(IF($C$3="Load",DVH($C$5,"netincome",$C53)*$B53,X53),"") -> 60458000000 | Y53: =iferror(X53/$D53,"") -> 0.30083696 | Z53: =iferror(if(X53<0,if(F53<0,0,F53),if(F53>X53,(F53-X53),0)),"") -> 22818000000 | AA53: =iferror(if(and(X53<0,F53<0),V53,V53-max(F53,X53)),"") -> 81515000000 | AB53: =iferror(D53-V53,"") -> 36175000000 | AC53: =IFERROR(__xludf.DUMMYFUNCTION("IF($C$3=""Load"",GOOGLEFINANCE(C4,""price"",today()-7*365,today(),""weekly""),Arrayformula(AC53:AD449))"),"Date") -> Date | AD53: =IFERROR(__xludf.DUMMYFUNCTION("""COMPUTED_VALUE"""),"Close") -> Close
C54: CAGR or Avg | D54: =iferror((D51/D43)^(1/8)-1,"") -> 0.24977761 | E54: =iferror(AVERAGE(E50:E53),"") -> 0.20490665 | F54: =iferror((F51/F43)^(1/8)-1,"") -> 0.23981961 | G54: =iferror(AVERAGE(G50:G53),"") -> 0.39926818 | H54: =iferror((H51/H43)^(1/8)-1,"") -> 0.24221077 | I54: =iferror((I51/I43)^(1/8)-1,"") -> 0.30273669 | J54: =iferror((J51/J43)^(1/8)-1,"") -> 0.22845368 | K54: =iferror((K51/K43)^(1/8)-1,"") -> 0.26209343 | L54: =iferror(AVERAGE(L50:L53),"") -> 0.73704796 | M54: =iferror((M51/M41)^(1/10)-1,"") | N54: =iferror(AVERAGE(N41:N53),"") -> -0.16306996 | O54: =iferror((O51/O41)^(1/10)-1,"") -> -0.0018929199 | P54: =iferror((P51/P41)^(1/10)-1,"") -> 0.21781745 | Q54: =iferror((Q51/Q41)^(1/10)-1,"") -> 0.22067255 | R54: =iferror(TRIMMEAN(R41:R53,0.4),"") -> 0.075729064 | S54: =iferror(TRIMMEAN(S41:S53,0.4),"") -> 22.394888 | T54: =iferror((T51/T41)^(1/10)-1,"") -> 0.27501393 | AC54: =IFERROR(__xludf.DUMMYFUNCTION("""COMPUTED_VALUE"""),43532.66666666667) -> 43532.667 | AD54: =IFERROR(__xludf.DUMMYFUNCTION("""COMPUTED_VALUE"""),169.6) -> 169.6
D55: =IFERROR(__xludf.DUMMYFUNCTION("sparkline(D43:D53,{""charttype"",""column"";""color"",""0044CC"";""ymin"",min(D43:D53,0);""lastcolor"",""red""})"),"") | E55: =IFERROR(__xludf.DUMMYFUNCTION("sparkline(E43:E53,{""charttype"",""column"";""color"",""0044CC"";""ymin"",min(E43:E53,0);""lastcolor"",""red""})"),"") | F55: =IFERROR(__xludf.DUMMYFUNCTION("sparkline(F43:F53,{""charttype"",""column"";""color"",""0044CC"";""ymin"",min(F43:F53,0);""lastcolor"",""red""})"),"") | G55: =IFERROR(__xludf.DUMMYFUNCTION("sparkline(G43:G53,{""charttype"",""column"";""color"",""0044CC"";""ymin"",min(G43:G53,0);""lastcolor"",""red""})"),"") | H55: =IFERROR(__xludf.DUMMYFUNCTION("sparkline(H43:H53,{""charttype"",""column"";""color"",""0044CC"";""ymin"",min(H43:H53,0);""lastcolor"",""red""})"),"") | I55: =IFERROR(__xludf.DUMMYFUNCTION("sparkline(I43:I53,{""charttype"",""column"";""color"",""0044CC"";""ymin"",min(I43:I53,0);""lastcolor"",""red""})"),"") | J55: =IFERROR(__xludf.DUMMYFUNCTION("sparkline(J43:J53,{""charttype"",""column"";""color"",""0044CC"";""ymin"",min(J43:J53,0);""lastcolor"",""red""})"),"") | K55: =IFERROR(__xludf.DUMMYFUNCTION("sparkline(K43:K53,{""charttype"",""column"";""color"",""0044CC"";""ymin"",min(K43:K53,0);""lastcolor"",""red""})"),"") | L55: =IFERROR(__xludf.DUMMYFUNCTION("sparkline(L43:L53,{""charttype"",""column"";""color"",""0044CC"";""ymin"",min(L43:L53,0);""lastcolor"",""red""})"),"") | M55: =IFERROR(__xludf.DUMMYFUNCTION("sparkline(M43:M53,{""charttype"",""column"";""color"",""0044CC"";""ymin"",min(M43:M53,0);""lastcolor"",""red""})"),"") | N55: =IFERROR(__xludf.DUMMYFUNCTION("sparkline(N43:N53,{""charttype"",""column"";""color"",""0044CC"";""ymin"",min(N43:N53,0);""lastcolor"",""red""})"),"") | O55: =IFERROR(__xludf.DUMMYFUNCTION("sparkline(O43:O53,{""charttype"",""column"";""color"",""0044CC"";""ymin"",min(O43:O53,0);""lastcolor"",""red""})"),"") | P55: =IFERROR(__xludf.DUMMYFUNCTION("sparkline(P43:P53,{""charttype"",""column"";""color"",""0044CC"";""ymin"",min(P43:P53,0);""lastcolor"",""red""})"),"") | Q55: =IFERROR(__xludf.DUMMYFUNCTION("sparkline(Q43:Q53,{""charttype"",""column"";""color"",""0044CC"";""ymin"",min(Q43:Q53,0);""lastcolor"",""red""})"),"") | R55: =IFERROR(__xludf.DUMMYFUNCTION("sparkline(R43:R53,{""charttype"",""column"";""color"",""0044CC"";""ymin"",min(R43:R53,0);""lastcolor"",""red""})"),"") | S55: =IFERROR(__xludf.DUMMYFUNCTION("sparkline(S43:S53,{""charttype"",""column"";""color"",""0044CC"";""ymin"",min(S43:S53,0);""lastcolor"",""red""})"),"") | T55: =IFERROR(__xludf.DUMMYFUNCTION("sparkline(T43:T53,{""charttype"",""column"";""color"",""0044CC"";""ymin"",min(T43:T53,0);""lastcolor"",""red""})"),"") | AC55: =IFERROR(__xludf.DUMMYFUNCTION("""COMPUTED_VALUE"""),43539.66666666667) -> 43539.667 | AD55: =IFERROR(__xludf.DUMMYFUNCTION("""COMPUTED_VALUE"""),165.98) -> 165.98
AC56: =IFERROR(__xludf.DUMMYFUNCTION("""COMPUTED_VALUE"""),43546.66666666667) -> 43546.667 | AD56: =IFERROR(__xludf.DUMMYFUNCTION("""COMPUTED_VALUE"""),164.34) -> 164.34
AC57: =IFERROR(__xludf.DUMMYFUNCTION("""COMPUTED_VALUE"""),43553.66666666667) -> 43553.667 | AD57: =IFERROR(__xludf.DUMMYFUNCTION("""COMPUTED_VALUE"""),166.69) -> 166.69
AC58: =IFERROR(__xludf.DUMMYFUNCTION("""COMPUTED_VALUE"""),43560.66666666667) -> 43560.667 | AD58: =IFERROR(__xludf.DUMMYFUNCTION("""COMPUTED_VALUE"""),175.72) -> 175.72
AC59: =IFERROR(__xludf.DUMMYFUNCTION("""COMPUTED_VALUE"""),43567.66666666667) -> 43567.667 | AD59: =IFERROR(__xludf.DUMMYFUNCTION("""COMPUTED_VALUE"""),179.1) -> 179.1
C60: 5-year 2030 Forecasted Data | AC60: =IFERROR(__xludf.DUMMYFUNCTION("""COMPUTED_VALUE"""),43573.66666666667) -> 43573.667 | AD60: =IFERROR(__xludf.DUMMYFUNCTION("""COMPUTED_VALUE"""),178.28) -> 178.28
D61: Revenue | E61: Revenue Y/Y ∆ | F61: Operating Income | G61: Operating Margin | H61: Adj. FCF Margin | I61: Adj. FCF | J61: PV of Adj. FCF | K61: 2029 EV/EBIT Multiple | N61: =S53 -> 20.559476 | P61: IRR | Q61: {=if(countif(G63:H67,"=0")=10,"NA",IRR({-1*P$53,I63,I64,I65,I66,I67+N65}))} -> 0.34080165 | R61: =IFERROR(Q61-0.03,) -> 0.31080165 | S61: – | T61: =IFERROR(Q61+0.02,) -> 0.36080165 | V61: s | AC61: =IFERROR(__xludf.DUMMYFUNCTION("""COMPUTED_VALUE"""),43581.66666666667) -> 43581.667 | AD61: =IFERROR(__xludf.DUMMYFUNCTION("""COMPUTED_VALUE"""),191.49) -> 191.49
K62: 2029 Enterprise Value | N62: =F67*N61 -> 4545313881942 | R62: Base Case | AC62: =IFERROR(__xludf.DUMMYFUNCTION("""COMPUTED_VALUE"""),43588.66666666667) -> 43588.667 | AD62: =IFERROR(__xludf.DUMMYFUNCTION("""COMPUTED_VALUE"""),195.47) -> 195.47
C63: 2026 | D63: =D$53*(1+E63) -> 245514210588 | E63: =E52 -> 0.22167038 | F63: =G63*D63 -> 101735822980 | G63: =G53 -> 0.41437855 | H63: =L52 -> 0.82135287 | I63: =H63*D63 -> 201653800427 | J63: =I63/(1+N$66)^(C63-C$63+1) -> 183321636752 | K63: Net Debt | N63: =M$53 -> 48024000000 | P63: Fair Value Today | Q63: =if(Q61="NA","-",(N67/P$53)*I$6) -> 1490.0751 | AC63: =IFERROR(__xludf.DUMMYFUNCTION("""COMPUTED_VALUE"""),43595.66666666667) -> 43595.667 | AD63: =IFERROR(__xludf.DUMMYFUNCTION("""COMPUTED_VALUE"""),188.34) -> 188.34
C64: =C63+1 -> 2027 | D64: =D63*(1+E64) -> 299937440168 | E64: =E63 -> 0.22167038 | F64: =G64*D64 -> 124287642026 | G64: =G63 -> 0.41437855 | H64: =H63 -> 0.82135287 | I64: =H64*D64 -> 246354476001 | J64: =I64/(1+N$66)^(C64-C$63+1) -> 203598740496 | K64: Adjustment | N64: 0 | R64: =IFERROR(Q63-(Q63*0.05),) -> 1415.5714 | S64: – | T64: =IFERROR(Q63+(Q63*0.05),) -> 1564.5789 | AC64: =IFERROR(__xludf.DUMMYFUNCTION("""COMPUTED_VALUE"""),43602.66666666667) -> 43602.667 | AD64: =IFERROR(__xludf.DUMMYFUNCTION("""COMPUTED_VALUE"""),185.3) -> 185.3
C65: =C64+1 -> 2028 | D65: =D64*(1+E65) -> 366424688001 | E65: =E64 -> 0.22167038 | F65: =G65*D65 -> 151838531483 | G65: =G64 -> 0.41437855 | H65: =H64 -> 0.82135287 | I65: =H65*D65 -> 300963967538 | J65: =I65/(1+N$66)^(C65-C$63+1) -> 226118683349 | K65: 2029 Market Cap | N65: =N62-N63+N64*1000000 -> 4497289881942 | AC65: =IFERROR(__xludf.DUMMYFUNCTION("""COMPUTED_VALUE"""),43609.66666666667) -> 43609.667 | AD65: =IFERROR(__xludf.DUMMYFUNCTION("""COMPUTED_VALUE"""),181.06) -> 181.06
C66: =C65+1 -> 2029 | D66: =D65*(1+E66) -> 443985942777 | E66: =E65-1% -> 0.21167038 | F66: =G66*D66 -> 183978251897 | G66: =G65 -> 0.41437855 | H66: =H65 -> 0.82135287 | I66: =H66*D66 -> 364669126412 | J66: =I66/(1+N$66)^(C66-C$63+1) -> 249073920096 | K66: Discount Rate | N66: 0.1 | P66: 5-Yr Price Change | Q66: {=if(Q61="NA","-",(npv(Q61,I63:I66,I67)*(1+Q61)^5+N65)/P$53-1)} -> 3.3333391 | AC66: =IFERROR(__xludf.DUMMYFUNCTION("""COMPUTED_VALUE"""),43616.66666666667) -> 43616.667 | AD66: =IFERROR(__xludf.DUMMYFUNCTION("""COMPUTED_VALUE"""),177.47) -> 177.47
C67: =C66+1 -> 2030 | D67: =D66*(1+E67) -> 533524758784 | E67: =E66-1% -> 0.20167039 | F67: =G67*D67 -> 221081216785 | G67: =G66 -> 0.41437855 | H67: =H66 -> 0.82135287 | I67: =H67*D67 -> 438212089527 | J67: =I67/(1+N$66)^(C67-C$63+1) -> 272095230410 | K67: PV of 2029 Market Cap + FCF | N67: =sum(J63:J67)+PV(N66,5,0,-1*N65) -> 3926671394779 | R67: =IF(Q66=0,Q66-0.03,) | S67: – | T67: =IF(Q66=0,Q66+0.02,) | AC67: =IFERROR(__xludf.DUMMYFUNCTION("""COMPUTED_VALUE"""),43623.66666666667) -> 43623.667 | AD67: =IFERROR(__xludf.DUMMYFUNCTION("""COMPUTED_VALUE"""),173.35) -> 173.35
AC68: =IFERROR(__xludf.DUMMYFUNCTION("""COMPUTED_VALUE"""),43630.66666666667) -> 43630.667 | AD68: =IFERROR(__xludf.DUMMYFUNCTION("""COMPUTED_VALUE"""),181.33) -> 181.33
D69: Revenue | E69: Revenue Y/Y ∆ | F69: Operating Income | G69: Operating Margin | H69: Adj. FCF Margin | I69: Adj. FCF | J69: PV of Adj. FCF | K69: 2029 EV/EBIT Multiple | N69: 0 | P69: IRR | Q69: {=if(countif(G71:H75,"=0")=10,"NA",IRR({-1*P$53,I71,I72,I73,I74,I75+N73}))} -> NA | R69: =IFERROR(Q69-0.03,) | S69: – | T69: =IFERROR(Q69+0.02,) | AC69: =IFERROR(__xludf.DUMMYFUNCTION("""COMPUTED_VALUE"""),43637.66666666667) -> 43637.667 | AD69: =IFERROR(__xludf.DUMMYFUNCTION("""COMPUTED_VALUE"""),191.14) -> 191.14
K70: 2029 Enterprise Value | N70: =F75*N69 -> 0 | R70: Bear Case | AC70: =IFERROR(__xludf.DUMMYFUNCTION("""COMPUTED_VALUE"""),43644.66666666667) -> 43644.667 | AD70: =IFERROR(__xludf.DUMMYFUNCTION("""COMPUTED_VALUE"""),193.0) -> 193
C71: =C63 -> 2026 | D71: =D$53*(1+E71) -> 200966000000 | E71: 0 | F71: =G71*D71 -> 0 | G71: 0 | H71: 0 | I71: =H71*D71 -> 0 | J71: =I71/(1+N$74)^(C71-C$71+1) -> 0 | K71: Net Debt | N71: =M$53 -> 48024000000 | P71: Fair Value Today | Q71: =if(Q69="NA","-",(N75/P$53)*I$6) -> - | AC71: =IFERROR(__xludf.DUMMYFUNCTION("""COMPUTED_VALUE"""),43651.66666666667) -> 43651.667 | AD71: =IFERROR(__xludf.DUMMYFUNCTION("""COMPUTED_VALUE"""),196.4) -> 196.4
C72: =C64 -> 2027 | D72: =D71*(1+E72) -> 200966000000 | E72: =E71 -> 0 | F72: =G72*D72 -> 0 | G72: =G71 -> 0 | H72: =H71 -> 0 | I72: =H72*D72 -> 0 | J72: =I72/(1+N$74)^(C72-C$71+1) -> 0 | K72: Adjustment | N72: 0 | R72: =IFERROR(Q71-(Q71*0.05),) | S72: – | T72: =IFERROR(Q71+(Q71*0.05),) | AC72: =IFERROR(__xludf.DUMMYFUNCTION("""COMPUTED_VALUE"""),43658.66666666667) -> 43658.667 | AD72: =IFERROR(__xludf.DUMMYFUNCTION("""COMPUTED_VALUE"""),204.87) -> 204.87
C73: =C65 -> 2028 | D73: =D72*(1+E73) -> 200966000000 | E73: =E72 -> 0 | F73: =G73*D73 -> 0 | G73: =G72 -> 0 | H73: =H72 -> 0 | I73: =H73*D73 -> 0 | J73: =I73/(1+N$74)^(C73-C$71+1) -> 0 | K73: 2029 Market Cap | N73: =N70-N71+N72*1000000 -> -48024000000 | AC73: =IFERROR(__xludf.DUMMYFUNCTION("""COMPUTED_VALUE"""),43665.66666666667) -> 43665.667 | AD73: =IFERROR(__xludf.DUMMYFUNCTION("""COMPUTED_VALUE"""),198.36) -> 198.36
C74: =C66 -> 2029 | D74: =D73*(1+E74) -> 198956340000 | E74: =E73-1% -> -0.01 | F74: =G74*D74 -> 0 | G74: =G73 -> 0 | H74: =H73 -> 0 | I74: =H74*D74 -> 0 | J74: =I74/(1+N$74)^(C74-C$71+1) -> 0 | K74: Discount Rate | N74: =N66 -> 0.1 | P74: 5-Yr Price Change | Q74: {=if(Q69="NA","-",(npv(Q69,I71:I74,I75)*(1+Q69)^5+N73)/P$53-1)} -> - | AC74: =IFERROR(__xludf.DUMMYFUNCTION("""COMPUTED_VALUE"""),43672.66666666667) -> 43672.667 | AD74: =IFERROR(__xludf.DUMMYFUNCTION("""COMPUTED_VALUE"""),199.75) -> 199.75
C75: =C67 -> 2030 | D75: =D74*(1+E75) -> 194977213200 | E75: =E74-1% -> -0.02 | F75: =G75*D75 -> 0 | G75: =G74 -> 0 | H75: =H74 -> 0 | I75: =H75*D75 -> 0 | J75: =I75/(1+N$74)^(C75-C$71+1) -> 0 | K75: PV of 2029 Market Cap + FCF | N75: =sum(J71:J75)+PV(N74,5,0,-1*N73) -> -29819125619 | R75: =IF(Q74=0,Q74-0.03,) | S75: – | T75: =IF(Q74=0,Q74+0.02,) | AC75: =IFERROR(__xludf.DUMMYFUNCTION("""COMPUTED_VALUE"""),43679.66666666667) -> 43679.667 | AD75: =IFERROR(__xludf.DUMMYFUNCTION("""COMPUTED_VALUE"""),189.02) -> 189.02
AC76: =IFERROR(__xludf.DUMMYFUNCTION("""COMPUTED_VALUE"""),43686.66666666667) -> 43686.667 | AD76: =IFERROR(__xludf.DUMMYFUNCTION("""COMPUTED_VALUE"""),187.85) -> 187.85
D77: Revenue | E77: Revenue Y/Y ∆ | F77: Operating Income | G77: Operating Margin | H77: Adj. FCF Margin | I77: Adj. FCF | J77: PV of Adj. FCF | K77: 2029 EV/EBIT Multiple | N77: 0 | P77: IRR | Q77: {=if(countif(G79:H83,"=0")=10,"NA",IRR({-1*P$53,I79,I80,I81,I82,I83+N81}))} -> NA | R77: =IFERROR(Q77-0.03,) | S77: – | T77: =IFERROR(Q77+0.02,) | AC77: =IFERROR(__xludf.DUMMYFUNCTION("""COMPUTED_VALUE"""),43693.66666666667) -> 43693.667 | AD77: =IFERROR(__xludf.DUMMYFUNCTION("""COMPUTED_VALUE"""),183.7) -> 183.7
K78: 2029 Enterprise Value | N78: =F83*N77 -> 0 | R78: Bull Case | AC78: =IFERROR(__xludf.DUMMYFUNCTION("""COMPUTED_VALUE"""),43700.66666666667) -> 43700.667 | AD78: =IFERROR(__xludf.DUMMYFUNCTION("""COMPUTED_VALUE"""),177.75) -> 177.75
C79: =C71 -> 2026 | D79: =D$53*(1+E79) -> 200966000000 | E79: 0 | F79: =G79*D79 -> 0 | G79: 0 | H79: 0 | I79: =H79*D79 -> 0 | J79: =I79/(1+N$82)^(C79-C$79+1) -> 0 | K79: Net Debt | N79: =M$53 -> 48024000000 | P79: Fair Value Today | Q79: =if(Q77="NA","-",(N83/P$53)*I$6) -> - | AC79: =IFERROR(__xludf.DUMMYFUNCTION("""COMPUTED_VALUE"""),43707.66666666667) -> 43707.667 | AD79: =IFERROR(__xludf.DUMMYFUNCTION("""COMPUTED_VALUE"""),185.67) -> 185.67
C80: =C72 -> 2027 | D80: =D79*(1+E80) -> 200966000000 | E80: =E79 -> 0 | F80: =G80*D80 -> 0 | G80: =G79 -> 0 | H80: =H79 -> 0 | I80: =H80*D80 -> 0 | J80: =I80/(1+N$82)^(C80-C$79+1) -> 0 | K80: Adjustment | N80: 0 | R80: =IFERROR(Q79-(Q79*0.05),) | S80: – | T80: =IFERROR(Q79+(Q79*0.05),) | AC80: =IFERROR(__xludf.DUMMYFUNCTION("""COMPUTED_VALUE"""),43714.66666666667) -> 43714.667 | AD80: =IFERROR(__xludf.DUMMYFUNCTION("""COMPUTED_VALUE"""),187.49) -> 187.49
C81: =C73 -> 2028 | D81: =D80*(1+E81) -> 200966000000 | E81: =E80 -> 0 | F81: =G81*D81 -> 0 | G81: =G80 -> 0 | H81: =H80 -> 0 | I81: =H81*D81 -> 0 | J81: =I81/(1+N$82)^(C81-C$79+1) -> 0 | K81: 2029 Market Cap | N81: =N78-N79+N80*1000000 -> -48024000000 | AC81: =IFERROR(__xludf.DUMMYFUNCTION("""COMPUTED_VALUE"""),43721.66666666667) -> 43721.667 | AD81: =IFERROR(__xludf.DUMMYFUNCTION("""COMPUTED_VALUE"""),187.19) -> 187.19
C82: =C74 -> 2029 | D82: =D81*(1+E82) -> 198956340000 | E82: =E81-1% -> -0.01 | F82: =G82*D82 -> 0 | G82: =G81 -> 0 | H82: =H81 -> 0 | I82: =H82*D82 -> 0 | J82: =I82/(1+N$82)^(C82-C$79+1) -> 0 | K82: Discount Rate | N82: =N66 -> 0.1 | P82: 5-Yr Price Change | Q82: {=if(Q77="NA","-",(npv(Q77,I79:I82,I83)*(1+Q77)^5+N81)/P$53-1)} -> - | AC82: =IFERROR(__xludf.DUMMYFUNCTION("""COMPUTED_VALUE"""),43728.66666666667) -> 43728.667 | AD82: =IFERROR(__xludf.DUMMYFUNCTION("""COMPUTED_VALUE"""),189.93) -> 189.93
C83: =C75 -> 2030 | D83: =D82*(1+E83) -> 194977213200 | E83: =E82-1% -> -0.02 | F83: =G83*D83 -> 0 | G83: =G82 -> 0 | H83: =H82 -> 0 | I83: =H83*D83 -> 0 | J83: =I83/(1+N$82)^(C83-C$79+1) -> 0 | K83: PV of 2029 Market Cap + FCF | N83: =sum(J79:J83)+PV(N82,5,0,-1*N81) -> -29819125619 | R83: =IF(Q82=0,Q82-0.03,) | S83: – | T83: =IF(Q82=0,Q82+0.02,) | AC83: =IFERROR(__xludf.DUMMYFUNCTION("""COMPUTED_VALUE"""),43735.66666666667) -> 43735.667 | AD83: =IFERROR(__xludf.DUMMYFUNCTION("""COMPUTED_VALUE"""),177.1) -> 177.1
AC84: =IFERROR(__xludf.DUMMYFUNCTION("""COMPUTED_VALUE"""),43742.66666666667) -> 43742.667 | AD84: =IFERROR(__xludf.DUMMYFUNCTION("""COMPUTED_VALUE"""),180.45) -> 180.45
C85: 3-year 2028 Forecasted Data | AC85: =IFERROR(__xludf.DUMMYFUNCTION("""COMPUTED_VALUE"""),43749.66666666667) -> 43749.667 | AD85: =IFERROR(__xludf.DUMMYFUNCTION("""COMPUTED_VALUE"""),184.19) -> 184.19
D86: Revenue | E86: Revenue Y/Y ∆ | F86: Operating Income | G86: Operating Margin | H86: Adj. FCF Margin | I86: Adj. FCF | J86: PV of Adj. FCF | K86: 2027 EV/EBIT Multiple | N86: =N61-2 -> 18.559476 | P86: IRR | Q86: {=if(countif(G88:H90,"=0")=10,"NA",IRR({-1*P$53,I88,I89,I90+N90}))} -> 0.29964059 | R86: =IFERROR(Q86-0.03,) -> 0.26964059 | S86: – | T86: =IFERROR(Q86+0.02,) -> 0.31964059 | V86: s | AC86: =IFERROR(__xludf.DUMMYFUNCTION("""COMPUTED_VALUE"""),43756.66666666667) -> 43756.667 | AD86: =IFERROR(__xludf.DUMMYFUNCTION("""COMPUTED_VALUE"""),185.85) -> 185.85
K87: 2027 Enterprise Value | N87: =F90*N86 -> 2749219748995 | R87: Base Case | AC87: =IFERROR(__xludf.DUMMYFUNCTION("""COMPUTED_VALUE"""),43763.66666666667) -> 43763.667 | AD87: =IFERROR(__xludf.DUMMYFUNCTION("""COMPUTED_VALUE"""),187.89) -> 187.89
C88: =C79 -> 2026 | D88: =D$53*(1+E88) -> 245514210588 | E88: =E63 -> 0.22167038 | F88: =G88*D88 -> 101735822980 | G88: =G63 -> 0.41437855 | H88: =H63 -> 0.82135287 | I88: =H88*D88 -> 201653800427 | J88: =I88/(1+N$66)^(C88-C$63+1) -> 183321636752 | K88: Net Debt | N88: =M$53 -> 48024000000 | P88: Fair Value Today | Q88: =if(Q86="NA","-",(N92/P$53)*I$6) -> 866.3727 | AC88: =IFERROR(__xludf.DUMMYFUNCTION("""COMPUTED_VALUE"""),43770.66666666667) -> 43770.667 | AD88: =IFERROR(__xludf.DUMMYFUNCTION("""COMPUTED_VALUE"""),193.62) -> 193.62
C89: =C80 -> 2027 | D89: =D88*(1+E89) -> 297482298062 | E89: =E88-1% -> 0.21167038 | F89: =G89*D89 -> 123270283796 | G89: =G88 -> 0.41437855 | H89: =H88 -> 0.82135287 | I89: =H89*D89 -> 244337937996 | J89: =I89/(1+N$66)^(C89-C$63+1) -> 201932180162 | K89: Adjustment | N89: 0 | R89: =IFERROR(Q88-(Q88*0.05),) -> 823.05406 | S89: – | T89: =IFERROR(Q88+(Q88*0.05),) -> 909.69133 | AC89: =IFERROR(__xludf.DUMMYFUNCTION("""COMPUTED_VALUE"""),43777.66666666667) -> 43777.667 | AD89: =IFERROR(__xludf.DUMMYFUNCTION("""COMPUTED_VALUE"""),190.84) -> 190.84
C90: =C81 -> 2028 | D90: =D89*(1+E90) -> 357475667638 | E90: =E89-1% -> 0.20167039 | F90: =G90*D90 -> 148130249387 | G90: =G89 -> 0.41437855 | H90: =H89 -> 0.82135287 | I90: =H90*D90 -> 293613664018 | J90: =I90/(1+N$66)^(C90-C$63+1) -> 220596291523 | K90: 2027 Market Cap | N90: =N87-N88+N89*1000000 -> 2701195748995 | AC90: =IFERROR(__xludf.DUMMYFUNCTION("""COMPUTED_VALUE"""),43784.66666666667) -> 43784.667 | AD90: =IFERROR(__xludf.DUMMYFUNCTION("""COMPUTED_VALUE"""),195.1) -> 195.1
K91: Discount Rate | N91: 0.1 | P91: 3-Yr Price Change | Q91: {=if(Q86="NA","-",(npv(Q86,I88:I89,I90)*(1+Q86)^3+N90)/P$53-1)} -> 1.1951783 | AC91: =IFERROR(__xludf.DUMMYFUNCTION("""COMPUTED_VALUE"""),43791.66666666667) -> 43791.667 | AD91: =IFERROR(__xludf.DUMMYFUNCTION("""COMPUTED_VALUE"""),198.82) -> 198.82
K92: PV of 2027 Market Cap + FCF | N92: =sum(J88:J90)+PV(N91,5,0,-1*N90) -> 2283080146745 | R92: =IF(Q91=0,Q91-0.03,) | S92: – | T92: =IF(Q91=0,Q91+0.02,) | AC92: =IFERROR(__xludf.DUMMYFUNCTION("""COMPUTED_VALUE"""),43798.54166666667) -> 43798.542 | AD92: =IFERROR(__xludf.DUMMYFUNCTION("""COMPUTED_VALUE"""),201.64) -> 201.64
AC93: =IFERROR(__xludf.DUMMYFUNCTION("""COMPUTED_VALUE"""),43805.66666666667) -> 43805.667 | AD93: =IFERROR(__xludf.DUMMYFUNCTION("""COMPUTED_VALUE"""),201.05) -> 201.05
D94: Revenue | E94: Revenue Y/Y ∆ | F94: Operating Income | G94: Operating Margin | H94: Adj. FCF Margin | I94: Adj. FCF | J94: PV of Adj. FCF | K94: 2027 EV/EBIT Multiple | N94: =N69-3 -> -3 | P94: IRR | Q94: {=if(countif(G96:H98,"=0")=10,"NA",IRR({-1*P$53,I96,I97,I98+N98}))} -> #NUM! | R94: =IFERROR(Q94-0.03,) | S94: – | T94: =IFERROR(Q94+0.02,) | AC94: =IFERROR(__xludf.DUMMYFUNCTION("""COMPUTED_VALUE"""),43812.66666666667) -> 43812.667 | AD94: =IFERROR(__xludf.DUMMYFUNCTION("""COMPUTED_VALUE"""),194.11) -> 194.11
K95: 2027 Enterprise Value | N95: =F98*N94 -> 0 | R95: Bear Case | AC95: =IFERROR(__xludf.DUMMYFUNCTION("""COMPUTED_VALUE"""),43819.66666666667) -> 43819.667 | AD95: =IFERROR(__xludf.DUMMYFUNCTION("""COMPUTED_VALUE"""),206.3) -> 206.3
C96: =C88 -> 2026 | D96: =D$53*(1+E96) -> 200966000000 | E96: =E71 -> 0 | F96: =G96*D96 -> 0 | G96: =G71 -> 0 | H96: =H71 -> 0 | I96: =H96*D96 -> 0 | J96: =I96/(1+N$74)^(C96-C$71+1) -> 0 | K96: Net Debt | N96: =M$53 -> 48024000000 | P96: Fair Value Today | Q96: =if(Q94="NA","-",(N100/P$53)*I$6) -> #NUM! | AC96: =IFERROR(__xludf.DUMMYFUNCTION("""COMPUTED_VALUE"""),43826.66666666667) -> 43826.667 | AD96: =IFERROR(__xludf.DUMMYFUNCTION("""COMPUTED_VALUE"""),208.1) -> 208.1
C97: =C89 -> 2027 | D97: =D96*(1+E97) -> 198956340000 | E97: =E96-1% -> -0.01 | F97: =G97*D97 -> 0 | G97: =G96 -> 0 | H97: =H96 -> 0 | I97: =H97*D97 -> 0 | J97: =I97/(1+N$74)^(C97-C$71+1) -> 0 | K97: Adjustment | N97: 0 | R97: =IFERROR(Q96-(Q96*0.05),) | S97: – | T97: =IFERROR(Q96+(Q96*0.05),) | AC97: =IFERROR(__xludf.DUMMYFUNCTION("""COMPUTED_VALUE"""),43833.66666666667) -> 43833.667 | AD97: =IFERROR(__xludf.DUMMYFUNCTION("""COMPUTED_VALUE"""),208.67) -> 208.67
C98: =C90 -> 2028 | D98: =D97*(1+E98) -> 194977213200 | E98: =E97-1% -> -0.02 | F98: =G98*D98 -> 0 | G98: =G97 -> 0 | H98: =H97 -> 0 | I98: =H98*D98 -> 0 | J98: =I98/(1+N$74)^(C98-C$71+1) -> 0 | K98: 2027 Market Cap | N98: =N95-N96+N97*1000000 -> -48024000000 | AC98: =IFERROR(__xludf.DUMMYFUNCTION("""COMPUTED_VALUE"""),43840.66666666667) -> 43840.667 | AD98: =IFERROR(__xludf.DUMMYFUNCTION("""COMPUTED_VALUE"""),218.06) -> 218.06
K99: Discount Rate | N99: =N91 -> 0.1 | P99: 3-Yr Price Change | Q99: {=if(Q94="NA","-",(npv(Q94,I96:I97,I98)*(1+Q94)^3+N98)/P$53-1)} -> #NUM! | AC99: =IFERROR(__xludf.DUMMYFUNCTION("""COMPUTED_VALUE"""),43847.66666666667) -> 43847.667 | AD99: =IFERROR(__xludf.DUMMYFUNCTION("""COMPUTED_VALUE"""),222.14) -> 222.14
K100: PV of 2027 Market Cap + FCF | N100: =sum(J96:J98)+PV(N99,5,0,-1*N98) -> -29819125619 | R100: =IF(Q99=0,Q99-0.03,) -> #NUM! | S100: – | T100: =IF(Q99=0,Q99+0.02,) -> #NUM! | AC100: =IFERROR(__xludf.DUMMYFUNCTION("""COMPUTED_VALUE"""),43854.66666666667) -> 43854.667 | AD100: =IFERROR(__xludf.DUMMYFUNCTION("""COMPUTED_VALUE"""),217.94) -> 217.94
AC101: =IFERROR(__xludf.DUMMYFUNCTION("""COMPUTED_VALUE"""),43861.66666666667) -> 43861.667 | AD101: =IFERROR(__xludf.DUMMYFUNCTION("""COMPUTED_VALUE"""),201.91) -> 201.91
D102: Revenue | E102: Revenue Y/Y ∆ | F102: Operating Income | G102: Operating Margin | H102: Adj. FCF Margin | I102: Adj. FCF | J102: PV of Adj. FCF | K102: 2027 EV/EBIT Multiple | N102: =N77-2 -> -2 | P102: IRR | Q102: {=if(countif(G104:H106,"=0")=10,"NA",IRR({-1*P$53,I104,I105,I106+N106}))} -> #NUM! | R102: =IFERROR(Q102-0.03,) | S102: – | T102: =IFERROR(Q102+0.02,) | AC102: =IFERROR(__xludf.DUMMYFUNCTION("""COMPUTED_VALUE"""),43868.66666666667) -> 43868.667 | AD102: =IFERROR(__xludf.DUMMYFUNCTION("""COMPUTED_VALUE"""),212.33) -> 212.33
K103: 2027 Enterprise Value | N103: =F106*N102 -> 0 | R103: Bull Case | AC103: =IFERROR(__xludf.DUMMYFUNCTION("""COMPUTED_VALUE"""),43875.66666666667) -> 43875.667 | AD103: =IFERROR(__xludf.DUMMYFUNCTION("""COMPUTED_VALUE"""),214.18) -> 214.18
C104: =C96 -> 2026 | D104: =D$53*(1+E104) -> 200966000000 | E104: =E79 -> 0 | F104: =G104*D104 -> 0 | G104: =G79 -> 0 | H104: =H79 -> 0 | I104: =H104*D104 -> 0 | J104: =I104/(1+N$82)^(C104-C$79+1) -> 0 | K104: Net Debt | N104: =M$53 -> 48024000000 | P104: Fair Value Today | Q104: =if(Q102="NA","-",(N108/P$53)*I$6) -> #NUM! | AC104: =IFERROR(__xludf.DUMMYFUNCTION("""COMPUTED_VALUE"""),43882.66666666667) -> 43882.667 | AD104: =IFERROR(__xludf.DUMMYFUNCTION("""COMPUTED_VALUE"""),210.18) -> 210.18
C105: =C97 -> 2027 | D105: =D104*(1+E105) -> 198956340000 | E105: =E104-1% -> -0.01 | F105: =G105*D105 -> 0 | G105: =G104 -> 0 | H105: =H104 -> 0 | I105: =H105*D105 -> 0 | J105: =I105/(1+N$82)^(C105-C$79+1) -> 0 | K105: Adjustment | N105: 0 | R105: =IFERROR(Q104-(Q104*0.05),) | S105: – | T105: =IFERROR(Q104+(Q104*0.05),) | AC105: =IFERROR(__xludf.DUMMYFUNCTION("""COMPUTED_VALUE"""),43889.66666666667) -> 43889.667 | AD105: =IFERROR(__xludf.DUMMYFUNCTION("""COMPUTED_VALUE"""),192.47) -> 192.47
C106: =C98 -> 2028 | D106: =D105*(1+E106) -> 194977213200 | E106: =E105-1% -> -0.02 | F106: =G106*D106 -> 0 | G106: =G105 -> 0 | H106: =H105 -> 0 | I106: =H106*D106 -> 0 | J106: =I106/(1+N$82)^(C106-C$79+1) -> 0 | K106: 2027 Market Cap | N106: =N103-N104+N105*1000000 -> -48024000000 | AC106: =IFERROR(__xludf.DUMMYFUNCTION("""COMPUTED_VALUE"""),43896.66666666667) -> 43896.667 | AD106: =IFERROR(__xludf.DUMMYFUNCTION("""COMPUTED_VALUE"""),181.09) -> 181.09
K107: Discount Rate | N107: =N91 -> 0.1 | P107: 3-Yr Price Change | Q107: {=if(Q102="NA","-",(npv(Q102,I104:I105,I106)*(1+Q102)^3+N106)/P$53-1)} -> #NUM! | AC107: =IFERROR(__xludf.DUMMYFUNCTION("""COMPUTED_VALUE"""),43903.66666666667) -> 43903.667 | AD107: =IFERROR(__xludf.DUMMYFUNCTION("""COMPUTED_VALUE"""),170.28) -> 170.28
K108: PV of 2027 Market Cap + FCF | N108: =sum(J104:J106)+PV(N107,5,0,-1*N106) -> -29819125619 | R108: =IF(Q107=0,Q107-0.03,) -> #NUM! | S108: – | T108: =IF(Q107=0,Q107+0.02,) -> #NUM! | AC108: =IFERROR(__xludf.DUMMYFUNCTION("""COMPUTED_VALUE"""),43910.66666666667) -> 43910.667 | AD108: =IFERROR(__xludf.DUMMYFUNCTION("""COMPUTED_VALUE"""),149.73) -> 149.73
AC109: =IFERROR(__xludf.DUMMYFUNCTION("""COMPUTED_VALUE"""),43917.66666666667) -> 43917.667 | AD109: =IFERROR(__xludf.DUMMYFUNCTION("""COMPUTED_VALUE"""),156.79) -> 156.79
C110: Questions to check yourself | P110: Analyst Ratings | AC110: =IFERROR(__xludf.DUMMYFUNCTION("""COMPUTED_VALUE"""),43924.66666666667) -> 43924.667 | AD110: =IFERROR(__xludf.DUMMYFUNCTION("""COMPUTED_VALUE"""),154.18) -> 154.18
C111: Can I understand the company? | N111: No | P111: Date | Q111: Action | R111: Analyst | S111: Rating | T111: Price Target | AC111: =IFERROR(__xludf.DUMMYFUNCTION("""COMPUTED_VALUE"""),43930.66666666667) -> 43930.667 | AD111: =IFERROR(__xludf.DUMMYFUNCTION("""COMPUTED_VALUE"""),175.19) -> 175.19
C112: Is revenue growing? Did you sanity check your revenue growth assumptions? | N112: No | P112: =IFERROR(__xludf.DUMMYFUNCTION("IF($C$3=""Static"",ARRAYFORMULA(P112:T116),if(ARRAY_CONSTRAIN(IMPORTHTML(""https://finviz.com/quote.ashx?t=""&C5,""table"",""11""),10,5)=""[Table]"", """",CHOOSEROWS(IMPORTHTML(""https://finviz.com/quote.ashx?t=""&C5,""table"",""11""),2,3,4,5,6)))"),0.0) -> 0 | AC112: =IFERROR(__xludf.DUMMYFUNCTION("""COMPUTED_VALUE"""),43938.66666666667) -> 43938.667 | AD112: =IFERROR(__xludf.DUMMYFUNCTION("""COMPUTED_VALUE"""),179.24) -> 179.24
C113: Can I predict the earnings/cash flow? | N113: No | AC113: =IFERROR(__xludf.DUMMYFUNCTION("""COMPUTED_VALUE"""),43945.66666666667) -> 43945.667 | AD113: =IFERROR(__xludf.DUMMYFUNCTION("""COMPUTED_VALUE"""),190.07) -> 190.07
C114: Are current earnings/FCF normal, not inflated by temporary tailwinds? | N114: No | AC114: =IFERROR(__xludf.DUMMYFUNCTION("""COMPUTED_VALUE"""),43952.66666666667) -> 43952.667 | AD114: =IFERROR(__xludf.DUMMYFUNCTION("""COMPUTED_VALUE"""),202.27) -> 202.27
C115: Are the company's earnings independent of commodity prices? | N115: No | AC115: =IFERROR(__xludf.DUMMYFUNCTION("""COMPUTED_VALUE"""),43959.66666666667) -> 43959.667 | AD115: =IFERROR(__xludf.DUMMYFUNCTION("""COMPUTED_VALUE"""),212.35) -> 212.35
C116: Is the debt reasonable / is balance sheet healthy? | N116: No | AC116: =IFERROR(__xludf.DUMMYFUNCTION("""COMPUTED_VALUE"""),43966.66666666667) -> 43966.667 | AD116: =IFERROR(__xludf.DUMMYFUNCTION("""COMPUTED_VALUE"""),210.88) -> 210.88
C117: Do the maturities on the debt seem manageable? | N117: No | P117: =IFERROR(__xludf.DUMMYFUNCTION("IF($C$3=""Load"",(REGEXREPLACE(QUERY(IMPORTHTML(""https://finviz.com/quote.ashx?t=""&$C$4,""table"",""9""),""select Col10 where Col9 = 'Avg Volume' ""),""\D+"","""")/REGEXREPLACE(QUERY(IMPORTHTML(""https://finviz.com/quote.ashx?t=""&$C$4,""table"",""9""),"&"""select Col10 where Col9 = 'Shs Float' ""),""\D+"","""")),N116)"),"No") -> No | AC117: =IFERROR(__xludf.DUMMYFUNCTION("""COMPUTED_VALUE"""),43973.66666666667) -> 43973.667 | AD117: =IFERROR(__xludf.DUMMYFUNCTION("""COMPUTED_VALUE"""),234.91) -> 234.91
C118: Does the company put its shareholders first? | N118: No | P118: Other Metrics | AC118: =IFERROR(__xludf.DUMMYFUNCTION("""COMPUTED_VALUE"""),43980.66666666667) -> 43980.667 | AD118: =IFERROR(__xludf.DUMMYFUNCTION("""COMPUTED_VALUE"""),225.09) -> 225.09
...

Sheet Currency Conversion
A1: Foreign Currency to USD Conversion
C3: USD | D3: CNY | E3: GBP | F3: KRW | G3: EUR | H3: JPY | I3: CAD | J3: BRL | K3: KZT | L3: DKK
B4: 2007 | C4: 1 | D4: 0.1314 | E4: 2 | F4: 0.001 | G4: 1.37 | H4: 0.0084745763 | I4: 0.93 | J4: 0.51282051 | K4: 0.0082 | L4: 0.17
B5: 2008 | C5: 1 | D5: 0.1441 | E5: 1.85 | F5: 0.00090909091 | G5: 1.47 | H5: 0.0096721153 | I5: 0.94 | J5: 0.54347826 | K5: 0.0083 | L5: 0.18
B6: 2009 | C6: 1 | D6: 0.1464 | E6: 1.6494 | F6: 0.0007911 | G6: 1.4145 | H6: 0.01035 | I6: 0.87013 | J6: 0.5 | K6: 0.0067 | L6: 0.16
B7: 2010 | C7: 1 | D7: 0.1477 | E7: 1.5161 | F7: 0.000816 | G7: 1.25049 | H7: 0.01141 | I7: 0.94422 | J7: 0.56818182 | K7: 0.0068 | L7: 0.17
B8: 2011 | C8: 1 | D8: 0.1548 | E8: 1.607 | F8: 0.0009385 | G8: 1.4524 | H8: 0.01237 | I8: 1.0429 | J8: 0.5988024 | K8: 0.0068 | L8: 0.18
B9: 2012 | C9: 1 | D9: 0.1585 | E9: 1.56817 | F9: 0.0008606 | G9: 1.2658 | H9: 0.01252 | I9: 0.98231 | J9: 0.51282051 | K9: 0.0067 | L9: 0.17
B10: 2013 | C10: 1 | D10: 0.1626 | E10: 1.5212 | F10: 0.0008797 | G10: 1.30636 | H10: 0.010032 | I10: 0.95219 | J10: 0.46296296 | K10: 0.0066 | L10: 0.17
B11: 2014 | C11: 1 | D11: 0.1629 | E11: 1.5603 | F11: 0.000988 | G11: 1.3679 | H11: 0.009847 | I11: 0.94021 | J11: 0.42553191 | K11: 0.0056 | L11: 0.17
B12: 2015 | C12: 1 | D12: 0.159 | E12: 1.71478 | F12: 0.0008876 | G12: 1.10375 | H12: 0.0081078 | I12: 0.79397 | J12: 0.3003003 | K12: 0.0047 | L12: 0.16
B13: 2016 | C13: 1 | D13: 0.1506 | E13: 1.3262 | F13: 0.0008688 | G13: 1.11383 | H13: 0.00975 | I13: 0.77446 | J13: 0.28735632 | K13: 0.0029 | L13: 0.15
B14: 2017 | C14: 1 | D14: 0.1481 | E14: 1.3027 | F14: 0.0008721 | G14: 1.1426 | H14: 0.0089 | I14: 0.77125 | J14: 0.31347962 | K14: 0.0031 | L14: 0.16
B15: 2018 | C15: 1 | D15: 0.1513 | E15: 1.32066 | F15: 0.0008953 | G15: 1.1677 | H15: 0.00903 | I15: 0.7608 | J15: 0.2739726 | K15: 0.0029 | L15: 0.16
... B22: 2025 | C22: 1 | D22: 0.1403 | E22: 1.3175 | F22: 0.0007 | G22: 1.1287 | H22: 0.0067 | I22: 0.7153 | J22: 0.1788 | K22: 0.0019 | L22: 0.1511
B23: TTM | C23: 1 | D23: 0.1403 | E23: 1.3175 | F23: 0.0007 | G23: 1.1287 | H23: 0.0067 | I23: 0.7153 | J23: 0.1788 | K23: 0.0019 | L23: 0.1511
B24: Today | C24: 1 | D24: 0.1403 | E24: 1.3175 | F24: 0.0007 | G24: 1.1287 | H24: 0.0067 | I24: 0.7153 | J24: 0.1788 | K24: 0.0019 | L24: 0.1511
B26: *Note conversion values are approximate for each calandar year, there will likely be discrepancies with company reported USD figures, especially if your company's fiscal year does not match the calandar year
